{
"meta":{"test_sets":[],"test_metrics":[],"learn_metrics":[{"best_value":"Min","name":"RMSE"}],"launch_mode":"Train","parameters":"","iteration_count":1000,"learn_sets":["learn"],"name":"experiment"},
"iterations":[
{"learn":[14.61268541],"iteration":0,"passed_time":0.1391224698,"remaining_time":138.9833473},
{"learn":[14.23196558],"iteration":1,"passed_time":0.1397168059,"remaining_time":69.71868614},
{"learn":[13.86674177],"iteration":2,"passed_time":0.1404378914,"remaining_time":46.67219257},
{"learn":[13.49946468],"iteration":3,"passed_time":0.1410088449,"remaining_time":35.11120237},
{"learn":[13.16661202],"iteration":4,"passed_time":0.1415799098,"remaining_time":28.17440204},
{"learn":[12.85632158],"iteration":5,"passed_time":0.1422227756,"remaining_time":23.56157316},
{"learn":[12.56784336],"iteration":6,"passed_time":0.142734936,"remaining_time":20.2479702},
{"learn":[12.31617801],"iteration":7,"passed_time":0.1431900662,"remaining_time":17.75556821},
{"learn":[12.01509946],"iteration":8,"passed_time":0.1437347065,"remaining_time":15.82678824},
{"learn":[11.71512571],"iteration":9,"passed_time":0.1442926966,"remaining_time":14.28497696},
{"learn":[11.43264457],"iteration":10,"passed_time":0.1450872817,"remaining_time":13.0446656},
{"learn":[11.17973129],"iteration":11,"passed_time":0.1458281874,"remaining_time":12.00652076},
{"learn":[10.93746433],"iteration":12,"passed_time":0.1465053195,"remaining_time":11.12313464},
{"learn":[10.69387075],"iteration":13,"passed_time":0.1472304323,"remaining_time":10.36922902},
{"learn":[10.4615922],"iteration":14,"passed_time":0.1479061767,"remaining_time":9.712505605},
{"learn":[10.2299235],"iteration":15,"passed_time":0.1485452002,"remaining_time":9.135529814},
{"learn":[10.01419731],"iteration":16,"passed_time":0.1492244737,"remaining_time":8.628685746},
{"learn":[9.795856918],"iteration":17,"passed_time":0.1498193854,"remaining_time":8.173479802},
{"learn":[9.60040151],"iteration":18,"passed_time":0.150402348,"remaining_time":7.765510703},
{"learn":[9.418664989],"iteration":19,"passed_time":0.1510409169,"remaining_time":7.40100493},
{"learn":[9.249278645],"iteration":20,"passed_time":0.1514895473,"remaining_time":7.06229842},
{"learn":[9.090113396],"iteration":21,"passed_time":0.151923663,"remaining_time":6.753697383},
{"learn":[8.909548708],"iteration":22,"passed_time":0.1523846001,"remaining_time":6.473032794},
{"learn":[8.740140208],"iteration":23,"passed_time":0.152819127,"remaining_time":6.214644499},
{"learn":[8.59377682],"iteration":24,"passed_time":0.1532285566,"remaining_time":5.975913709},
{"learn":[8.453885414],"iteration":25,"passed_time":0.1536342565,"remaining_time":5.755375608},
{"learn":[8.317732234],"iteration":26,"passed_time":0.1540786731,"remaining_time":5.552538847},
{"learn":[8.180896085],"iteration":27,"passed_time":0.1544804762,"remaining_time":5.362679387},
{"learn":[8.053220863],"iteration":28,"passed_time":0.1549429698,"remaining_time":5.187918059},
{"learn":[7.924234474],"iteration":29,"passed_time":0.1553658786,"remaining_time":5.023496743},
{"learn":[7.818879511],"iteration":30,"passed_time":0.1557867349,"remaining_time":4.869591812},
{"learn":[7.719346395],"iteration":31,"passed_time":0.1562157079,"remaining_time":4.725525163},
{"learn":[7.624163594],"iteration":32,"passed_time":0.1567193767,"remaining_time":4.592352645},
{"learn":[7.524952543],"iteration":33,"passed_time":0.157157514,"remaining_time":4.465122308},
{"learn":[7.424464745],"iteration":34,"passed_time":0.1575807912,"remaining_time":4.344727528},
{"learn":[7.327482321],"iteration":35,"passed_time":0.1579800539,"remaining_time":4.230354777},
{"learn":[7.238666841],"iteration":36,"passed_time":0.1584061541,"remaining_time":4.122841253},
{"learn":[7.158842395],"iteration":37,"passed_time":0.1588212327,"remaining_time":4.020684891},
{"learn":[7.074348246],"iteration":38,"passed_time":0.1592345284,"remaining_time":3.923702096},
{"learn":[6.992269093],"iteration":39,"passed_time":0.159619736,"remaining_time":3.830873663},
{"learn":[6.925219745],"iteration":40,"passed_time":0.1601469973,"remaining_time":3.745877326},
{"learn":[6.86013671],"iteration":41,"passed_time":0.1608130703,"remaining_time":3.668069556},
{"learn":[6.786739622],"iteration":42,"passed_time":0.1613665318,"remaining_time":3.591343511},
{"learn":[6.73057926],"iteration":43,"passed_time":0.1619468863,"remaining_time":3.518664166},
{"learn":[6.666356486],"iteration":44,"passed_time":0.1624703795,"remaining_time":3.447982499},
{"learn":[6.606182832],"iteration":45,"passed_time":0.1630437033,"remaining_time":3.38138463},
{"learn":[6.547854615],"iteration":46,"passed_time":0.1635412051,"remaining_time":3.316058903},
{"learn":[6.49240675],"iteration":47,"passed_time":0.1640092378,"remaining_time":3.252849884},
{"learn":[6.431317261],"iteration":48,"passed_time":0.1645377919,"remaining_time":3.193376329},
{"learn":[6.377586395],"iteration":49,"passed_time":0.1649624461,"remaining_time":3.134286476},
{"learn":[6.327558015],"iteration":50,"passed_time":0.1654185965,"remaining_time":3.078083296},
{"learn":[6.282040317],"iteration":51,"passed_time":0.1659481887,"remaining_time":3.025363133},
{"learn":[6.237655841],"iteration":52,"passed_time":0.1663901921,"remaining_time":2.973047394},
{"learn":[6.192792003],"iteration":53,"passed_time":0.166798538,"remaining_time":2.922063276},
{"learn":[6.150579347],"iteration":54,"passed_time":0.1672333445,"remaining_time":2.873372919},
{"learn":[6.115693845],"iteration":55,"passed_time":0.1676895263,"remaining_time":2.8267663},
{"learn":[6.078780782],"iteration":56,"passed_time":0.1682621845,"remaining_time":2.783705965},
{"learn":[6.045146957],"iteration":57,"passed_time":0.1687041465,"remaining_time":2.739988035},
{"learn":[6.008080327],"iteration":58,"passed_time":0.1692103626,"remaining_time":2.698761885},
{"learn":[5.977575734],"iteration":59,"passed_time":0.1697364606,"remaining_time":2.659204549},
{"learn":[5.948036502],"iteration":60,"passed_time":0.1701949465,"remaining_time":2.619886143},
{"learn":[5.914888282],"iteration":61,"passed_time":0.1706792738,"remaining_time":2.582212239},
{"learn":[5.884957796],"iteration":62,"passed_time":0.171122308,"remaining_time":2.545104803},
{"learn":[5.849539885],"iteration":63,"passed_time":0.1715692741,"remaining_time":2.509200634},
{"learn":[5.821387627],"iteration":64,"passed_time":0.1720458264,"remaining_time":2.474813041},
{"learn":[5.797012279],"iteration":65,"passed_time":0.1724658563,"remaining_time":2.440653179},
{"learn":[5.768685095],"iteration":66,"passed_time":0.1729003017,"remaining_time":2.407701216},
{"learn":[5.755484587],"iteration":67,"passed_time":0.1731220432,"remaining_time":2.372790357},
{"learn":[5.731887055],"iteration":68,"passed_time":0.1735566475,"remaining_time":2.341757085},
{"learn":[5.707148487],"iteration":69,"passed_time":0.1740565901,"remaining_time":2.312466125},
{"learn":[5.685365039],"iteration":70,"passed_time":0.1745082571,"remaining_time":2.283354519},
{"learn":[5.663541834],"iteration":71,"passed_time":0.1750283755,"remaining_time":2.255921285},
{"learn":[5.638108797],"iteration":72,"passed_time":0.1755803991,"remaining_time":2.229630548},
{"learn":[5.619204893],"iteration":73,"passed_time":0.1760866122,"remaining_time":2.203462201},
{"learn":[5.598472793],"iteration":74,"passed_time":0.1765750767,"remaining_time":2.177759279},
{"learn":[5.577007075],"iteration":75,"passed_time":0.1770583563,"remaining_time":2.152656858},
{"learn":[5.562637084],"iteration":76,"passed_time":0.1775556129,"remaining_time":2.128361438},
{"learn":[5.54729991],"iteration":77,"passed_time":0.1780547398,"remaining_time":2.104698334},
{"learn":[5.530737623],"iteration":78,"passed_time":0.1785875421,"remaining_time":2.082014257},
{"learn":[5.513704873],"iteration":79,"passed_time":0.1791368147,"remaining_time":2.060073369},
{"learn":[5.501575529],"iteration":80,"passed_time":0.1796947581,"remaining_time":2.038759045},
{"learn":[5.484080734],"iteration":81,"passed_time":0.1801548006,"remaining_time":2.016854963},
{"learn":[5.472178894],"iteration":82,"passed_time":0.1805892816,"remaining_time":1.995185196},
{"learn":[5.458923342],"iteration":83,"passed_time":0.1809979607,"remaining_time":1.973739666},
{"learn":[5.451382371],"iteration":84,"passed_time":0.1812854692,"remaining_time":1.951484757},
{"learn":[5.441410748],"iteration":85,"passed_time":0.1817218481,"remaining_time":1.931322897},
{"learn":[5.434047468],"iteration":86,"passed_time":0.1820133874,"remaining_time":1.910094514},
{"learn":[5.422107497],"iteration":87,"passed_time":0.1824331324,"remaining_time":1.890670645},
{"learn":[5.40731265],"iteration":88,"passed_time":0.1828992685,"remaining_time":1.872148692},
{"learn":[5.396360181],"iteration":89,"passed_time":0.1833177407,"remaining_time":1.853546045},
{"learn":[5.383793239],"iteration":90,"passed_time":0.1837647842,"remaining_time":1.835628449},
{"learn":[5.369605034],"iteration":91,"passed_time":0.184170713,"remaining_time":1.817684863},
{"learn":[5.357467333],"iteration":92,"passed_time":0.1846214495,"remaining_time":1.800555427},
{"learn":[5.341109968],"iteration":93,"passed_time":0.1850713371,"remaining_time":1.783772674},
{"learn":[5.330529276],"iteration":94,"passed_time":0.1855666331,"remaining_time":1.767766347},
{"learn":[5.319862075],"iteration":95,"passed_time":0.1859946127,"remaining_time":1.751449269},
{"learn":[5.313052243],"iteration":96,"passed_time":0.1864255684,"remaining_time":1.735487508},
{"learn":[5.299677207],"iteration":97,"passed_time":0.1868788284,"remaining_time":1.720047992},
{"learn":[5.287546698],"iteration":98,"passed_time":0.1872862951,"remaining_time":1.704494464},
{"learn":[5.279803754],"iteration":99,"passed_time":0.1877237033,"remaining_time":1.68951333},
{"learn":[5.272254612],"iteration":100,"passed_time":0.1881247788,"remaining_time":1.674496794},
{"learn":[5.268813888],"iteration":101,"passed_time":0.1883349833,"remaining_time":1.658086422},
{"learn":[5.258113767],"iteration":102,"passed_time":0.1887302146,"remaining_time":1.643601966},
{"learn":[5.251018576],"iteration":103,"passed_time":0.1891550373,"remaining_time":1.629643398},
{"learn":[5.24171237],"iteration":104,"passed_time":0.1897739381,"remaining_time":1.617596901},
{"learn":[5.233984943],"iteration":105,"passed_time":0.1903494511,"remaining_time":1.605400088},
{"learn":[5.226240449],"iteration":106,"passed_time":0.1909071793,"remaining_time":1.593272066},
{"learn":[5.220541644],"iteration":107,"passed_time":0.1914130067,"remaining_time":1.580929648},
{"learn":[5.211712096],"iteration":108,"passed_time":0.1919419418,"remaining_time":1.568993304},
{"learn":[5.203388597],"iteration":109,"passed_time":0.1924419544,"remaining_time":1.557030358},
{"learn":[5.196026544],"iteration":110,"passed_time":0.1929901019,"remaining_time":1.545659465},
{"learn":[5.188716772],"iteration":111,"passed_time":0.1934747689,"remaining_time":1.533978525},
{"learn":[5.182163132],"iteration":112,"passed_time":0.1939565681,"remaining_time":1.522473238},
{"learn":[5.17764747],"iteration":113,"passed_time":0.1943712063,"remaining_time":1.510639376},
{"learn":[5.170548056],"iteration":114,"passed_time":0.1948029073,"remaining_time":1.499135417},
{"learn":[5.165901827],"iteration":115,"passed_time":0.1951473563,"remaining_time":1.48715744},
{"learn":[5.160333668],"iteration":116,"passed_time":0.1955573841,"remaining_time":1.475873249},
{"learn":[5.148953243],"iteration":117,"passed_time":0.1960407767,"remaining_time":1.465321737},
{"learn":[5.144729126],"iteration":118,"passed_time":0.1963913511,"remaining_time":1.453956137},
{"learn":[5.139939946],"iteration":119,"passed_time":0.1968637765,"remaining_time":1.443667694},
{"learn":[5.132898872],"iteration":120,"passed_time":0.1972794732,"remaining_time":1.433129396},
{"learn":[5.129073077],"iteration":121,"passed_time":0.1977542731,"remaining_time":1.423182392},
{"learn":[5.127123916],"iteration":122,"passed_time":0.1979573528,"remaining_time":1.41145202},
{"learn":[5.121282057],"iteration":123,"passed_time":0.1983525725,"remaining_time":1.401264948},
{"learn":[5.114489821],"iteration":124,"passed_time":0.1987722594,"remaining_time":1.391405816},
{"learn":[5.107777291],"iteration":125,"passed_time":0.1991962021,"remaining_time":1.381726037},
{"learn":[5.103518754],"iteration":126,"passed_time":0.1997022868,"remaining_time":1.372756665},
{"learn":[5.101133351],"iteration":127,"passed_time":0.2000611104,"remaining_time":1.362916315},
{"learn":[5.096462705],"iteration":128,"passed_time":0.2005412779,"remaining_time":1.354042272},
{"learn":[5.08562082],"iteration":129,"passed_time":0.2010809688,"remaining_time":1.345695714},
{"learn":[5.080483682],"iteration":130,"passed_time":0.2015633876,"remaining_time":1.337088426},
{"learn":[5.07437499],"iteration":131,"passed_time":0.2021168323,"remaining_time":1.329071291},
{"learn":[5.070683732],"iteration":132,"passed_time":0.2026133759,"remaining_time":1.320795465},
{"learn":[5.06432037],"iteration":133,"passed_time":0.2030932818,"remaining_time":1.312528224},
{"learn":[5.057436484],"iteration":134,"passed_time":0.203495991,"remaining_time":1.30388172},
{"learn":[5.053254656],"iteration":135,"passed_time":0.2039894773,"remaining_time":1.29593315},
{"learn":[5.04801663],"iteration":136,"passed_time":0.204536566,"remaining_time":1.288431069},
{"learn":[5.045680836],"iteration":137,"passed_time":0.2049620324,"remaining_time":1.280270087},
{"learn":[5.041857933],"iteration":138,"passed_time":0.2055086284,"remaining_time":1.272970712},
{"learn":[5.035264888],"iteration":139,"passed_time":0.2060005672,"remaining_time":1.265432056},
{"learn":[5.028771948],"iteration":140,"passed_time":0.206498425,"remaining_time":1.258029412},
{"learn":[5.024912247],"iteration":141,"passed_time":0.2070213247,"remaining_time":1.250875328},
{"learn":[5.02239068],"iteration":142,"passed_time":0.2077216132,"remaining_time":1.24487708},
{"learn":[5.017110572],"iteration":143,"passed_time":0.2083357243,"remaining_time":1.238440139},
{"learn":[5.010707886],"iteration":144,"passed_time":0.2088837826,"remaining_time":1.231694028},
{"learn":[5.004389868],"iteration":145,"passed_time":0.2094042059,"remaining_time":1.224871177},
{"learn":[4.997628683],"iteration":146,"passed_time":0.209890305,"remaining_time":1.217934899},
{"learn":[4.991497851],"iteration":147,"passed_time":0.2103758079,"remaining_time":1.211082354},
{"learn":[4.988345253],"iteration":148,"passed_time":0.2108637574,"remaining_time":1.204329245},
{"learn":[4.98460423],"iteration":149,"passed_time":0.2113124437,"remaining_time":1.197437181},
{"learn":[4.982441783],"iteration":150,"passed_time":0.2117542632,"remaining_time":1.190591851},
{"learn":[4.977461771],"iteration":151,"passed_time":0.212150304,"remaining_time":1.18357538},
{"learn":[4.973601586],"iteration":152,"passed_time":0.2125546926,"remaining_time":1.176691664},
{"learn":[4.968328804],"iteration":153,"passed_time":0.2129962656,"remaining_time":1.170096368},
{"learn":[4.9640736],"iteration":154,"passed_time":0.2134433512,"remaining_time":1.163610527},
{"learn":[4.960865882],"iteration":155,"passed_time":0.2138666544,"remaining_time":1.157073438},
{"learn":[4.957014156],"iteration":156,"passed_time":0.2143147904,"remaining_time":1.150747569},
{"learn":[4.952244852],"iteration":157,"passed_time":0.2147664804,"remaining_time":1.144515041},
{"learn":[4.949695675],"iteration":158,"passed_time":0.2151790317,"remaining_time":1.138148212},
{"learn":[4.946584698],"iteration":159,"passed_time":0.2155912904,"remaining_time":1.131854274},
{"learn":[4.940192834],"iteration":160,"passed_time":0.215987279,"remaining_time":1.125548616},
{"learn":[4.936727994],"iteration":161,"passed_time":0.216413236,"remaining_time":1.119470937},
{"learn":[4.932342063],"iteration":162,"passed_time":0.216859496,"remaining_time":1.11356686},
{"learn":[4.925830838],"iteration":163,"passed_time":0.2173196067,"remaining_time":1.107799946},
{"learn":[4.922571773],"iteration":164,"passed_time":0.2177282092,"remaining_time":1.101836695},
{"learn":[4.918395814],"iteration":165,"passed_time":0.2181713031,"remaining_time":1.096113655},
{"learn":[4.911142452],"iteration":166,"passed_time":0.2185761804,"remaining_time":1.090263223},
{"learn":[4.908276131],"iteration":167,"passed_time":0.2190917967,"remaining_time":1.085026041},
{"learn":[4.904584645],"iteration":168,"passed_time":0.2196779813,"remaining_time":1.080191731},
{"learn":[4.89795517],"iteration":169,"passed_time":0.2204942373,"remaining_time":1.076530688},
{"learn":[4.895556491],"iteration":170,"passed_time":0.2211725309,"remaining_time":1.072234083},
{"learn":[4.890591233],"iteration":171,"passed_time":0.2217965814,"remaining_time":1.067718427},
{"learn":[4.884629277],"iteration":172,"passed_time":0.2223817807,"remaining_time":1.063062038},
{"learn":[4.880550786],"iteration":173,"passed_time":0.2230346717,"remaining_time":1.058773786},
{"learn":[4.876384842],"iteration":174,"passed_time":0.2236308405,"remaining_time":1.054259677},
{"learn":[4.872638238],"iteration":175,"passed_time":0.2243057823,"remaining_time":1.05015889},
{"learn":[4.869137118],"iteration":176,"passed_time":0.2249841452,"remaining_time":1.04611272},
{"learn":[4.863587157],"iteration":177,"passed_time":0.2257063052,"remaining_time":1.042306645},
{"learn":[4.858028614],"iteration":178,"passed_time":0.2264726805,"remaining_time":1.038737825},
{"learn":[4.853838176],"iteration":179,"passed_time":0.2269289817,"remaining_time":1.033787583},
{"learn":[4.853462329],"iteration":180,"passed_time":0.227131016,"remaining_time":1.027736476},
{"learn":[4.851573196],"iteration":181,"passed_time":0.227539463,"remaining_time":1.022677367},
{"learn":[4.848442087],"iteration":182,"passed_time":0.2280141921,"remaining_time":1.017965},
{"learn":[4.845547104],"iteration":183,"passed_time":0.2285113844,"remaining_time":1.013398313},
{"learn":[4.839868817],"iteration":184,"passed_time":0.2290965504,"remaining_time":1.009263182},
{"learn":[4.836336958],"iteration":185,"passed_time":0.2296755405,"remaining_time":1.005139193},
{"learn":[4.831124789],"iteration":186,"passed_time":0.2302428592,"remaining_time":1.001002377},
{"learn":[4.827407333],"iteration":187,"passed_time":0.2307105925,"remaining_time":0.9964734101},
{"learn":[4.824088918],"iteration":188,"passed_time":0.2312303992,"remaining_time":0.9922108665},
{"learn":[4.820934539],"iteration":189,"passed_time":0.2317132415,"remaining_time":0.9878301349},
{"learn":[4.816975227],"iteration":190,"passed_time":0.2322277439,"remaining_time":0.9836243184},
{"learn":[4.812340486],"iteration":191,"passed_time":0.232679574,"remaining_time":0.9791932074},
{"learn":[4.806402747],"iteration":192,"passed_time":0.233101645,"remaining_time":0.974678899},
{"learn":[4.801521788],"iteration":193,"passed_time":0.2335932059,"remaining_time":0.9704954843},
{"learn":[4.797601172],"iteration":194,"passed_time":0.2341857185,"remaining_time":0.9667666839},
{"learn":[4.792694629],"iteration":195,"passed_time":0.2348461471,"remaining_time":0.963348481},
{"learn":[4.789794613],"iteration":196,"passed_time":0.235423468,"remaining_time":0.9596195167},
{"learn":[4.785367055],"iteration":197,"passed_time":0.2360243284,"remaining_time":0.9560177344},
{"learn":[4.780376856],"iteration":198,"passed_time":0.2365958333,"remaining_time":0.9523279523},
{"learn":[4.776691261],"iteration":199,"passed_time":0.2372770338,"remaining_time":0.9491081351},
{"learn":[4.773470753],"iteration":200,"passed_time":0.2379821544,"remaining_time":0.9460086636},
{"learn":[4.77207327],"iteration":201,"passed_time":0.2385469737,"remaining_time":0.9423786387},
{"learn":[4.767347177],"iteration":202,"passed_time":0.2390291336,"remaining_time":0.9384542833},
{"learn":[4.763983068],"iteration":203,"passed_time":0.2394978587,"remaining_time":0.9345112528},
{"learn":[4.761588849],"iteration":204,"passed_time":0.2399116576,"remaining_time":0.9303891112},
{"learn":[4.758558086],"iteration":205,"passed_time":0.2403141837,"remaining_time":0.9262595236},
{"learn":[4.753678804],"iteration":206,"passed_time":0.2407109581,"remaining_time":0.9221439121},
{"learn":[4.746510889],"iteration":207,"passed_time":0.2411155207,"remaining_time":0.9180937134},
{"learn":[4.744840601],"iteration":208,"passed_time":0.241520277,"remaining_time":0.9140791344},
{"learn":[4.741702222],"iteration":209,"passed_time":0.2420172192,"remaining_time":0.9104457294},
{"learn":[4.739352853],"iteration":210,"passed_time":0.2424545508,"remaining_time":0.9066191496},
{"learn":[4.735539287],"iteration":211,"passed_time":0.2429032509,"remaining_time":0.9028668003},
{"learn":[4.730726751],"iteration":212,"passed_time":0.2432953826,"remaining_time":0.8989364607},
{"learn":[4.726416092],"iteration":213,"passed_time":0.2437212439,"remaining_time":0.8951630732},
{"learn":[4.721293082],"iteration":214,"passed_time":0.2441287917,"remaining_time":0.8913539605},
{"learn":[4.718443695],"iteration":215,"passed_time":0.2445531541,"remaining_time":0.8876373743},
{"learn":[4.711627962],"iteration":216,"passed_time":0.2449869183,"remaining_time":0.8839850555},
{"learn":[4.709790764],"iteration":217,"passed_time":0.2453866099,"remaining_time":0.8802400412},
{"learn":[4.706913073],"iteration":218,"passed_time":0.2457749882,"remaining_time":0.876485232},
{"learn":[4.703846389],"iteration":219,"passed_time":0.2461773343,"remaining_time":0.8728105491},
{"learn":[4.701001135],"iteration":220,"passed_time":0.2466130714,"remaining_time":0.8692831792},
{"learn":[4.700380864],"iteration":221,"passed_time":0.2470094576,"remaining_time":0.8656457566},
{"learn":[4.695837486],"iteration":222,"passed_time":0.2474702123,"remaining_time":0.8622616815},
{"learn":[4.691242996],"iteration":223,"passed_time":0.2480349474,"remaining_time":0.8592639248},
{"learn":[4.690284609],"iteration":224,"passed_time":0.248634831,"remaining_time":0.8564088622},
{"learn":[4.68827119],"iteration":225,"passed_time":0.2492200471,"remaining_time":0.8535235243},
{"learn":[4.686922425],"iteration":226,"passed_time":0.249734947,"remaining_time":0.8504190045},
{"learn":[4.686085874],"iteration":227,"passed_time":0.2501777449,"remaining_time":0.8470930661},
{"learn":[4.683230741],"iteration":228,"passed_time":0.2506508852,"remaining_time":0.8438944652},
{"learn":[4.6773487],"iteration":229,"passed_time":0.2511568272,"remaining_time":0.8408293779},
{"learn":[4.671462906],"iteration":230,"passed_time":0.2517020104,"remaining_time":0.8379170824},
{"learn":[4.664799601],"iteration":231,"passed_time":0.2521520722,"remaining_time":0.834710308},
{"learn":[4.660979386],"iteration":232,"passed_time":0.2525931787,"remaining_time":0.8314977171},
{"learn":[4.656281279],"iteration":233,"passed_time":0.2531078186,"remaining_time":0.8285495258},
{"learn":[4.651997094],"iteration":234,"passed_time":0.2536115824,"remaining_time":0.8255866405},
{"learn":[4.650151977],"iteration":235,"passed_time":0.2541011532,"remaining_time":0.8225986484},
{"learn":[4.648478046],"iteration":236,"passed_time":0.2545140261,"remaining_time":0.8193848182},
{"learn":[4.646364602],"iteration":237,"passed_time":0.2549291775,"remaining_time":0.8162018203},
{"learn":[4.642635873],"iteration":238,"passed_time":0.2553579765,"remaining_time":0.81308544},
{"learn":[4.640860821],"iteration":239,"passed_time":0.2557881726,"remaining_time":0.8099958798},
{"learn":[4.639446822],"iteration":240,"passed_time":0.2561719671,"remaining_time":0.8067822534},
{"learn":[4.637120072],"iteration":241,"passed_time":0.2566101618,"remaining_time":0.8037624078},
{"learn":[4.633769267],"iteration":242,"passed_time":0.2570776715,"remaining_time":0.8008551331},
{"learn":[4.630491517],"iteration":243,"passed_time":0.2575835158,"remaining_time":0.7980866309},
{"learn":[4.627813333],"iteration":244,"passed_time":0.2581809081,"remaining_time":0.7956187167},
{"learn":[4.622496304],"iteration":245,"passed_time":0.2588129963,"remaining_time":0.7932723545},
{"learn":[4.618979301],"iteration":246,"passed_time":0.2593704679,"remaining_time":0.790712398},
{"learn":[4.616563458],"iteration":247,"passed_time":0.2598566474,"remaining_time":0.7879524147},
{"learn":[4.614759385],"iteration":248,"passed_time":0.260289452,"remaining_time":0.7850497125},
{"learn":[4.61251363],"iteration":249,"passed_time":0.2607412101,"remaining_time":0.7822236304},
{"learn":[4.608796693],"iteration":250,"passed_time":0.2611939716,"remaining_time":0.779419461},
{"learn":[4.60847774],"iteration":251,"passed_time":0.2616636134,"remaining_time":0.7766840589},
{"learn":[4.605195659],"iteration":252,"passed_time":0.2621657149,"remaining_time":0.7740624073},
{"learn":[4.60103766],"iteration":253,"passed_time":0.2626800649,"remaining_time":0.7714934189},
{"learn":[4.599325598],"iteration":254,"passed_time":0.263204332,"remaining_time":0.768969519},
{"learn":[4.597012808],"iteration":255,"passed_time":0.2637219687,"remaining_time":0.7664419715},
{"learn":[4.594161533],"iteration":256,"passed_time":0.2642766315,"remaining_time":0.7640371096},
{"learn":[4.592197259],"iteration":257,"passed_time":0.2647661636,"remaining_time":0.7614592767},
{"learn":[4.58952828],"iteration":258,"passed_time":0.2652538059,"remaining_time":0.7588921629},
{"learn":[4.585816572],"iteration":259,"passed_time":0.2657433101,"remaining_time":0.7563463441},
{"learn":[4.582934052],"iteration":260,"passed_time":0.2662038374,"remaining_time":0.753734237},
{"learn":[4.582234842],"iteration":261,"passed_time":0.266644466,"remaining_time":0.7510825035},
{"learn":[4.57571562],"iteration":262,"passed_time":0.2670665408,"remaining_time":0.7483955916},
{"learn":[4.571197349],"iteration":263,"passed_time":0.2674917219,"remaining_time":0.7457344975},
{"learn":[4.56723703],"iteration":264,"passed_time":0.2679452041,"remaining_time":0.7431687735},
{"learn":[4.560335567],"iteration":265,"passed_time":0.2683902755,"remaining_time":0.7405957225},
{"learn":[4.554709345],"iteration":266,"passed_time":0.2688427045,"remaining_time":0.7380588105},
{"learn":[4.552806306],"iteration":267,"passed_time":0.2693021818,"remaining_time":0.7355567056},
{"learn":[4.550766241],"iteration":268,"passed_time":0.2697204732,"remaining_time":0.7329578659},
{"learn":[4.549216045],"iteration":269,"passed_time":0.2701216399,"remaining_time":0.7303288783},
{"learn":[4.547687452],"iteration":270,"passed_time":0.2705937456,"remaining_time":0.7279071606},
{"learn":[4.545642435],"iteration":271,"passed_time":0.2710416595,"remaining_time":0.7254350298},
{"learn":[4.543930359],"iteration":272,"passed_time":0.2715123659,"remaining_time":0.7230384249},
{"learn":[4.541029943],"iteration":273,"passed_time":0.2719454101,"remaining_time":0.7205560867},
{"learn":[4.537781449],"iteration":274,"passed_time":0.2723378039,"remaining_time":0.7179814829},
{"learn":[4.53066128],"iteration":275,"passed_time":0.2727448378,"remaining_time":0.7154610963},
{"learn":[4.526763956],"iteration":276,"passed_time":0.2731803727,"remaining_time":0.713030359},
{"learn":[4.522036004],"iteration":277,"passed_time":0.2736143076,"remaining_time":0.7106098206},
{"learn":[4.515307629],"iteration":278,"passed_time":0.2740281693,"remaining_time":0.708151649},
{"learn":[4.51109143],"iteration":279,"passed_time":0.2744591427,"remaining_time":0.7057520811},
{"learn":[4.508233494],"iteration":280,"passed_time":0.2748951792,"remaining_time":0.7033794798},
{"learn":[4.502555629],"iteration":281,"passed_time":0.2753206429,"remaining_time":0.7009936936},
{"learn":[4.500081355],"iteration":282,"passed_time":0.2757663009,"remaining_time":0.698672925},
{"learn":[4.495281743],"iteration":283,"passed_time":0.2763024911,"remaining_time":0.6965936042},
{"learn":[4.492138869],"iteration":284,"passed_time":0.2769416509,"remaining_time":0.6947834399},
{"learn":[4.491708261],"iteration":285,"passed_time":0.2773837726,"remaining_time":0.6924895581},
{"learn":[4.489398865],"iteration":286,"passed_time":0.2778054476,"remaining_time":0.6901577844},
{"learn":[4.485796373],"iteration":287,"passed_time":0.278326994,"remaining_time":0.6880861795},
{"learn":[4.479542205],"iteration":288,"passed_time":0.2789191339,"remaining_time":0.6861989766},
{"learn":[4.475986993],"iteration":289,"passed_time":0.2794272149,"remaining_time":0.6841149055},
{"learn":[4.468661855],"iteration":290,"passed_time":0.279885746,"remaining_time":0.6819209413},
{"learn":[4.463785664],"iteration":291,"passed_time":0.2803339536,"remaining_time":0.6797138327},
{"learn":[4.460445831],"iteration":292,"passed_time":0.2808462579,"remaining_time":0.6776733937},
{"learn":[4.45692492],"iteration":293,"passed_time":0.2813582644,"remaining_time":0.6756426348},
{"learn":[4.454031688],"iteration":294,"passed_time":0.2819613183,"remaining_time":0.6738397606},
{"learn":[4.451672391],"iteration":295,"passed_time":0.2824670155,"remaining_time":0.6718134423},
{"learn":[4.45031553],"iteration":296,"passed_time":0.2829324072,"remaining_time":0.6697019605},
{"learn":[4.446782666],"iteration":297,"passed_time":0.2833672114,"remaining_time":0.6675294712},
{"learn":[4.444369689],"iteration":298,"passed_time":0.2837909236,"remaining_time":0.6653426002},
{"learn":[4.44411683],"iteration":299,"passed_time":0.2841922419,"remaining_time":0.6631152312},
{"learn":[4.440876943],"iteration":300,"passed_time":0.284604447,"remaining_time":0.6609252773},
{"learn":[4.439336453],"iteration":301,"passed_time":0.2850131445,"remaining_time":0.6587389895},
{"learn":[4.436666901],"iteration":302,"passed_time":0.2854051912,"remaining_time":0.656526133},
{"learn":[4.433043336],"iteration":303,"passed_time":0.2858026756,"remaining_time":0.6543377048},
{"learn":[4.431419305],"iteration":304,"passed_time":0.286244774,"remaining_time":0.6522626816},
{"learn":[4.428859646],"iteration":305,"passed_time":0.286678702,"remaining_time":0.6501798013},
{"learn":[4.424552441],"iteration":306,"passed_time":0.2870691658,"remaining_time":0.6480095501},
{"learn":[4.422706391],"iteration":307,"passed_time":0.2874970106,"remaining_time":0.6459348419},
{"learn":[4.421427994],"iteration":308,"passed_time":0.2879138729,"remaining_time":0.6438462335},
{"learn":[4.418733158],"iteration":309,"passed_time":0.2884933454,"remaining_time":0.6421303495},
{"learn":[4.415656941],"iteration":310,"passed_time":0.2889507741,"remaining_time":0.6401513933},
{"learn":[4.410747417],"iteration":311,"passed_time":0.2893858953,"remaining_time":0.638133},
{"learn":[4.408126521],"iteration":312,"passed_time":0.2898061512,"remaining_time":0.6360920955},
{"learn":[4.407843853],"iteration":313,"passed_time":0.2902161184,"remaining_time":0.6340390358},
{"learn":[4.405219398],"iteration":314,"passed_time":0.2906766385,"remaining_time":0.6321063408},
{"learn":[4.402708465],"iteration":315,"passed_time":0.2911485182,"remaining_time":0.630207552},
{"learn":[4.40104971],"iteration":316,"passed_time":0.291572837,"remaining_time":0.6282152922},
{"learn":[4.400830038],"iteration":317,"passed_time":0.2920089753,"remaining_time":0.6262582426},
{"learn":[4.39784288],"iteration":318,"passed_time":0.2924193431,"remaining_time":0.6242557136},
{"learn":[4.393741845],"iteration":319,"passed_time":0.2928429167,"remaining_time":0.6222911979},
{"learn":[4.393425936],"iteration":320,"passed_time":0.2933795843,"remaining_time":0.620575507},
{"learn":[4.390505974],"iteration":321,"passed_time":0.2938828292,"remaining_time":0.6187967647},
{"learn":[4.390305136],"iteration":322,"passed_time":0.2943516845,"remaining_time":0.6169538404},
{"learn":[4.38568203],"iteration":323,"passed_time":0.2948427626,"remaining_time":0.6151657639},
{"learn":[4.383057135],"iteration":324,"passed_time":0.2952672935,"remaining_time":0.6132474557},
{"learn":[4.380662684],"iteration":325,"passed_time":0.2957139349,"remaining_time":0.6113840249},
{"learn":[4.37805727],"iteration":326,"passed_time":0.2961425594,"remaining_time":0.6094921787},
{"learn":[4.373708319],"iteration":327,"passed_time":0.2965680346,"remaining_time":0.6076028026},
{"learn":[4.36887921],"iteration":328,"passed_time":0.2969950584,"remaining_time":0.6057254838},
{"learn":[4.367895929],"iteration":329,"passed_time":0.2973976588,"remaining_time":0.6038073678},
{"learn":[4.362140573],"iteration":330,"passed_time":0.2978525754,"remaining_time":0.6020041478},
{"learn":[4.361931924],"iteration":331,"passed_time":0.2983184982,"remaining_time":0.6002311951},
{"learn":[4.359656377],"iteration":332,"passed_time":0.2987507674,"remaining_time":0.5983986842},
{"learn":[4.354281355],"iteration":333,"passed_time":0.2992503346,"remaining_time":0.5967087511},
{"learn":[4.348589447],"iteration":334,"passed_time":0.2997680314,"remaining_time":0.5950619131},
{"learn":[4.346355698],"iteration":335,"passed_time":0.3002979617,"remaining_time":0.593445972},
{"learn":[4.343894047],"iteration":336,"passed_time":0.3008109944,"remaining_time":0.5918032323},
{"learn":[4.341561356],"iteration":337,"passed_time":0.3012819605,"remaining_time":0.5900847865},
{"learn":[4.338869061],"iteration":338,"passed_time":0.3017668147,"remaining_time":0.5884007803},
{"learn":[4.333720063],"iteration":339,"passed_time":0.3022972298,"remaining_time":0.5868122696},
{"learn":[4.330892223],"iteration":340,"passed_time":0.3028698027,"remaining_time":0.5853114369},
{"learn":[4.328311474],"iteration":341,"passed_time":0.3033640085,"remaining_time":0.5836652561},
{"learn":[4.324580133],"iteration":342,"passed_time":0.3039543617,"remaining_time":0.5822099581},
{"learn":[4.323354432],"iteration":343,"passed_time":0.3044505538,"remaining_time":0.5805801258},
{"learn":[4.323159553],"iteration":344,"passed_time":0.3048563884,"remaining_time":0.5787853171},
{"learn":[4.318639682],"iteration":345,"passed_time":0.3053001196,"remaining_time":0.5770701682},
{"learn":[4.312712208],"iteration":346,"passed_time":0.3057552605,"remaining_time":0.5753838188},
{"learn":[4.311461062],"iteration":347,"passed_time":0.3062317875,"remaining_time":0.5737446134},
{"learn":[4.311178356],"iteration":348,"passed_time":0.3066862346,"remaining_time":0.5720708846},
{"learn":[4.311102505],"iteration":349,"passed_time":0.3070988801,"remaining_time":0.5703264916},
{"learn":[4.310232308],"iteration":350,"passed_time":0.3074789955,"remaining_time":0.5685295386},
{"learn":[4.305128197],"iteration":351,"passed_time":0.3080032094,"remaining_time":0.5670059082},
{"learn":[4.304595496],"iteration":352,"passed_time":0.3085894583,"remaining_time":0.5656016417},
{"learn":[4.3004992],"iteration":353,"passed_time":0.309131075,"remaining_time":0.5641205492},
{"learn":[4.297581524],"iteration":354,"passed_time":0.3096060947,"remaining_time":0.5625237496},
{"learn":[4.297355825],"iteration":355,"passed_time":0.3101212668,"remaining_time":0.5610058872},
{"learn":[4.295758715],"iteration":356,"passed_time":0.3106432574,"remaining_time":0.5595059231},
{"learn":[4.292500657],"iteration":357,"passed_time":0.3111157127,"remaining_time":0.5579225909},
{"learn":[4.290797586],"iteration":358,"passed_time":0.3115920804,"remaining_time":0.5563524332},
{"learn":[4.286410608],"iteration":359,"passed_time":0.3120764881,"remaining_time":0.5548026455},
{"learn":[4.280278245],"iteration":360,"passed_time":0.312518843,"remaining_time":0.5531843232},
{"learn":[4.279941283],"iteration":361,"passed_time":0.3129205098,"remaining_time":0.551500788},
{"learn":[4.274426275],"iteration":362,"passed_time":0.3133245446,"remaining_time":0.5498284709},
{"learn":[4.273567658],"iteration":363,"passed_time":0.3137644778,"remaining_time":0.5482258459},
{"learn":[4.269488271],"iteration":364,"passed_time":0.3142069445,"remaining_time":0.5466339994},
{"learn":[4.266838205],"iteration":365,"passed_time":0.314620205,"remaining_time":0.5449978414},
{"learn":[4.263456509],"iteration":366,"passed_time":0.3150249337,"remaining_time":0.5433536323},
{"learn":[4.260360204],"iteration":367,"passed_time":0.3154724589,"remaining_time":0.5417896577},
{"learn":[4.255120549],"iteration":368,"passed_time":0.3158989551,"remaining_time":0.5401957741},
{"learn":[4.252582211],"iteration":369,"passed_time":0.3163737542,"remaining_time":0.5386904464},
{"learn":[4.247857931],"iteration":370,"passed_time":0.3169965476,"remaining_time":0.537441586},
{"learn":[4.245288911],"iteration":371,"passed_time":0.3175304749,"remaining_time":0.5360460706},
{"learn":[4.24048515],"iteration":372,"passed_time":0.3180404985,"remaining_time":0.5346149935},
{"learn":[4.2378365],"iteration":373,"passed_time":0.3185334142,"remaining_time":0.5331602067},
{"learn":[4.236751063],"iteration":374,"passed_time":0.3189955843,"remaining_time":0.5316593072},
{"learn":[4.233240093],"iteration":375,"passed_time":0.3194599279,"remaining_time":0.53016754},
{"learn":[4.230358421],"iteration":376,"passed_time":0.3199354332,"remaining_time":0.5286996682},
{"learn":[4.225853583],"iteration":377,"passed_time":0.3204236534,"remaining_time":0.5272579694},
{"learn":[4.224702126],"iteration":378,"passed_time":0.3208423201,"remaining_time":0.5257073372},
{"learn":[4.224361982],"iteration":379,"passed_time":0.3212614571,"remaining_time":0.5241634299},
{"learn":[4.223787954],"iteration":380,"passed_time":0.3216766942,"remaining_time":0.5226190911},
{"learn":[4.22144054],"iteration":381,"passed_time":0.3221267751,"remaining_time":0.5211370341},
{"learn":[4.217739335],"iteration":382,"passed_time":0.3227489259,"remaining_time":0.5199375647},
{"learn":[4.215611665],"iteration":383,"passed_time":0.3233553354,"remaining_time":0.5187158506},
{"learn":[4.210236863],"iteration":384,"passed_time":0.3239216826,"remaining_time":0.5174333371},
{"learn":[4.208454294],"iteration":385,"passed_time":0.3243842594,"remaining_time":0.5159894695},
{"learn":[4.207446501],"iteration":386,"passed_time":0.3248335453,"remaining_time":0.5145296209},
{"learn":[4.204985442],"iteration":387,"passed_time":0.3252884221,"remaining_time":0.5130837998},
{"learn":[4.202796622],"iteration":388,"passed_time":0.3258014773,"remaining_time":0.5117344541},
{"learn":[4.199774004],"iteration":389,"passed_time":0.3262949521,"remaining_time":0.5103587713},
{"learn":[4.199458358],"iteration":390,"passed_time":0.3267525224,"remaining_time":0.5089316782},
{"learn":[4.19751254],"iteration":391,"passed_time":0.3272203974,"remaining_time":0.5075255144},
{"learn":[4.195201346],"iteration":392,"passed_time":0.3276619742,"remaining_time":0.5060835072},
{"learn":[4.190593508],"iteration":393,"passed_time":0.3281690462,"remaining_time":0.5047473146},
{"learn":[4.187212054],"iteration":394,"passed_time":0.3286859047,"remaining_time":0.5034303097},
{"learn":[4.184984466],"iteration":395,"passed_time":0.3291980049,"remaining_time":0.5021100883},
{"learn":[4.182832144],"iteration":396,"passed_time":0.3297020184,"remaining_time":0.5007816552},
{"learn":[4.179752812],"iteration":397,"passed_time":0.3301925102,"remaining_time":0.4994369124},
{"learn":[4.17878934],"iteration":398,"passed_time":0.3305999516,"remaining_time":0.4979713556},
{"learn":[4.174548229],"iteration":399,"passed_time":0.3310290133,"remaining_time":0.49654352},
{"learn":[4.168872556],"iteration":400,"passed_time":0.3314721624,"remaining_time":0.495141709},
{"learn":[4.163926494],"iteration":401,"passed_time":0.3320620546,"remaining_time":0.4939629568},
{"learn":[4.159485076],"iteration":402,"passed_time":0.3328817218,"remaining_time":0.4931275134},
{"learn":[4.155926102],"iteration":403,"passed_time":0.3336348686,"remaining_time":0.4921940141},
{"learn":[4.153540115],"iteration":404,"passed_time":0.334169434,"remaining_time":0.4909402795},
{"learn":[4.150983044],"iteration":405,"passed_time":0.3348881859,"remaining_time":0.4899595626},
{"learn":[4.146539132],"iteration":406,"passed_time":0.3354761396,"remaining_time":0.4887895597},
{"learn":[4.144869174],"iteration":407,"passed_time":0.3359711733,"remaining_time":0.4874875848},
{"learn":[4.142825962],"iteration":408,"passed_time":0.3365033342,"remaining_time":0.4862432042},
{"learn":[4.142467378],"iteration":409,"passed_time":0.3369894238,"remaining_time":0.4849360001},
{"learn":[4.141800768],"iteration":410,"passed_time":0.3375672367,"remaining_time":0.4837642395},
{"learn":[4.140107084],"iteration":411,"passed_time":0.3381267754,"remaining_time":0.4825692814},
{"learn":[4.136243196],"iteration":412,"passed_time":0.3386005001,"remaining_time":0.4812554323},
{"learn":[4.133618439],"iteration":413,"passed_time":0.3391615911,"remaining_time":0.4800693053},
{"learn":[4.131053025],"iteration":414,"passed_time":0.3396886648,"remaining_time":0.4788382383},
{"learn":[4.128379975],"iteration":415,"passed_time":0.3402330791,"remaining_time":0.4776348995},
{"learn":[4.127068571],"iteration":416,"passed_time":0.3407811972,"remaining_time":0.4764398992},
{"learn":[4.125969877],"iteration":417,"passed_time":0.3413005207,"remaining_time":0.475207902},
{"learn":[4.123893633],"iteration":418,"passed_time":0.3417108272,"remaining_time":0.4738281399},
{"learn":[4.119643722],"iteration":419,"passed_time":0.3421748805,"remaining_time":0.472527216},
{"learn":[4.11465686],"iteration":420,"passed_time":0.34265163,"remaining_time":0.4712477287},
{"learn":[4.111565986],"iteration":421,"passed_time":0.3431191627,"remaining_time":0.4699594219},
{"learn":[4.106322452],"iteration":422,"passed_time":0.3435511148,"remaining_time":0.4686264616},
{"learn":[4.104222175],"iteration":423,"passed_time":0.3439945182,"remaining_time":0.4673133077},
{"learn":[4.103008002],"iteration":424,"passed_time":0.3443944817,"remaining_time":0.4659454752},
{"learn":[4.099176337],"iteration":425,"passed_time":0.3447951942,"remaining_time":0.4645831959},
{"learn":[4.096525716],"iteration":426,"passed_time":0.3452287279,"remaining_time":0.4632694638},
{"learn":[4.094967724],"iteration":427,"passed_time":0.345737788,"remaining_time":0.4620607821},
{"learn":[4.094683584],"iteration":428,"passed_time":0.3463082406,"remaining_time":0.4609370755},
{"learn":[4.091096563],"iteration":429,"passed_time":0.3468434194,"remaining_time":0.4597691838},
{"learn":[4.089178677],"iteration":430,"passed_time":0.3473413232,"remaining_time":0.4585550183},
{"learn":[4.085335077],"iteration":431,"passed_time":0.347887437,"remaining_time":0.457407556},
{"learn":[4.084852122],"iteration":432,"passed_time":0.3483578432,"remaining_time":0.4561637346},
{"learn":[4.080322952],"iteration":433,"passed_time":0.3487870152,"remaining_time":0.4548697019},
{"learn":[4.077449519],"iteration":434,"passed_time":0.3492235618,"remaining_time":0.4535892239},
{"learn":[4.076568374],"iteration":435,"passed_time":0.3496637891,"remaining_time":0.4523173785},
{"learn":[4.076071793],"iteration":436,"passed_time":0.3500948214,"remaining_time":0.451037493},
{"learn":[4.075027644],"iteration":437,"passed_time":0.3505247325,"remaining_time":0.4497600449},
{"learn":[4.07020837],"iteration":438,"passed_time":0.3509372784,"remaining_time":0.448464267},
{"learn":[4.06833694],"iteration":439,"passed_time":0.3514031787,"remaining_time":0.4472404092},
{"learn":[4.063936568],"iteration":440,"passed_time":0.3518762669,"remaining_time":0.4460291002},
{"learn":[4.061734926],"iteration":441,"passed_time":0.3524344128,"remaining_time":0.4449285121},
{"learn":[4.060815619],"iteration":442,"passed_time":0.3529785258,"remaining_time":0.4438127288},
{"learn":[4.056407489],"iteration":443,"passed_time":0.3535116088,"remaining_time":0.4426857083},
{"learn":[4.05238936],"iteration":444,"passed_time":0.3540511553,"remaining_time":0.4415694185},
{"learn":[4.049685254],"iteration":445,"passed_time":0.354593948,"remaining_time":0.440459747},
{"learn":[4.045162016],"iteration":446,"passed_time":0.3551564635,"remaining_time":0.4393770119},
{"learn":[4.042955482],"iteration":447,"passed_time":0.3556435066,"remaining_time":0.4382036063},
{"learn":[4.041467663],"iteration":448,"passed_time":0.356132009,"remaining_time":0.4370350489},
{"learn":[4.038920476],"iteration":449,"passed_time":0.3565777015,"remaining_time":0.4358171908},
{"learn":[4.036694383],"iteration":450,"passed_time":0.3570244781,"remaining_time":0.4346040765},
{"learn":[4.034999007],"iteration":451,"passed_time":0.3574475815,"remaining_time":0.4333656519},
{"learn":[4.031928018],"iteration":452,"passed_time":0.3579452298,"remaining_time":0.4322208404},
{"learn":[4.028718143],"iteration":453,"passed_time":0.3583676125,"remaining_time":0.4309883622},
{"learn":[4.027401978],"iteration":454,"passed_time":0.3587821611,"remaining_time":0.4297500611},
{"learn":[4.025930598],"iteration":455,"passed_time":0.3591919614,"remaining_time":0.4285097084},
{"learn":[4.021074523],"iteration":456,"passed_time":0.3597563193,"remaining_time":0.4274566332},
{"learn":[4.020268486],"iteration":457,"passed_time":0.360242765,"remaining_time":0.4263134904},
{"learn":[4.017986361],"iteration":458,"passed_time":0.3608054532,"remaining_time":0.4252630723},
{"learn":[4.014814804],"iteration":459,"passed_time":0.3613259485,"remaining_time":0.4241652439},
{"learn":[4.009704796],"iteration":460,"passed_time":0.3618964574,"remaining_time":0.4231283959},
{"learn":[4.008440457],"iteration":461,"passed_time":0.3624143292,"remaining_time":0.4220322707},
{"learn":[4.004854849],"iteration":462,"passed_time":0.3629291643,"remaining_time":0.4209351214},
{"learn":[4.000898028],"iteration":463,"passed_time":0.3634103856,"remaining_time":0.4198016524},
{"learn":[3.996617985],"iteration":464,"passed_time":0.3638939693,"remaining_time":0.4186737066},
{"learn":[3.995443319],"iteration":465,"passed_time":0.3644070184,"remaining_time":0.4175822915},
{"learn":[3.990771995],"iteration":466,"passed_time":0.3648856738,"remaining_time":0.4164540987},
{"learn":[3.989249359],"iteration":467,"passed_time":0.3653171304,"remaining_time":0.4152750285},
{"learn":[3.986599538],"iteration":468,"passed_time":0.3657764262,"remaining_time":0.4141306659},
{"learn":[3.985628919],"iteration":469,"passed_time":0.3661928565,"remaining_time":0.4129408808},
{"learn":[3.985086112],"iteration":470,"passed_time":0.3665963009,"remaining_time":0.4117397944},
{"learn":[3.98466839],"iteration":471,"passed_time":0.36703839,"remaining_time":0.4105853177},
{"learn":[3.984233894],"iteration":472,"passed_time":0.3675667388,"remaining_time":0.4095299606},
{"learn":[3.981855845],"iteration":473,"passed_time":0.3681065634,"remaining_time":0.4084895619},
{"learn":[3.978684264],"iteration":474,"passed_time":0.3686473242,"remaining_time":0.4074523057},
{"learn":[3.974361269],"iteration":475,"passed_time":0.3691367326,"remaining_time":0.4063606048},
{"learn":[3.972074049],"iteration":476,"passed_time":0.3696656118,"remaining_time":0.4053147064},
{"learn":[3.97191982],"iteration":477,"passed_time":0.3701962348,"remaining_time":0.4042728757},
{"learn":[3.969616848],"iteration":478,"passed_time":0.3707460102,"remaining_time":0.4032540111},
{"learn":[3.968533527],"iteration":479,"passed_time":0.3713681564,"remaining_time":0.4023155027},
{"learn":[3.967568753],"iteration":480,"passed_time":0.3717921535,"remaining_time":0.4011645066},
{"learn":[3.966232553],"iteration":481,"passed_time":0.3722169295,"remaining_time":0.400017364},
{"learn":[3.961522393],"iteration":482,"passed_time":0.3726281489,"remaining_time":0.3988587018},
{"learn":[3.955829553],"iteration":483,"passed_time":0.3730264842,"remaining_time":0.3976893922},
{"learn":[3.954248095],"iteration":484,"passed_time":0.3734859944,"remaining_time":0.3965882209},
{"learn":[3.951922606],"iteration":485,"passed_time":0.3739211433,"remaining_time":0.3954639252},
{"learn":[3.94978202],"iteration":486,"passed_time":0.3744948546,"remaining_time":0.3944884198},
{"learn":[3.949518999],"iteration":487,"passed_time":0.3750246835,"remaining_time":0.3934685204},
{"learn":[3.945431216],"iteration":488,"passed_time":0.3755051095,"remaining_time":0.3923989999},
{"learn":[3.943249086],"iteration":489,"passed_time":0.375961145,"remaining_time":0.3913064978},
{"learn":[3.941981548],"iteration":490,"passed_time":0.3764033168,"remaining_time":0.3902022164},
{"learn":[3.936600517],"iteration":491,"passed_time":0.3768441836,"remaining_time":0.389099279},
{"learn":[3.934476885],"iteration":492,"passed_time":0.3772586128,"remaining_time":0.3879718391},
{"learn":[3.93045798],"iteration":493,"passed_time":0.3776964912,"remaining_time":0.3868713047},
{"learn":[3.925977375],"iteration":494,"passed_time":0.3781037388,"remaining_time":0.3857421982},
{"learn":[3.92457993],"iteration":495,"passed_time":0.3785026577,"remaining_time":0.3846075393},
{"learn":[3.919849146],"iteration":496,"passed_time":0.3789412024,"remaining_time":0.3835159453},
{"learn":[3.919681964],"iteration":497,"passed_time":0.3793171331,"remaining_time":0.3823638571},
{"learn":[3.917633027],"iteration":498,"passed_time":0.3797078281,"remaining_time":0.3812297032},
{"learn":[3.916616419],"iteration":499,"passed_time":0.3801589445,"remaining_time":0.3801589445},
{"learn":[3.912896166],"iteration":500,"passed_time":0.3806611532,"remaining_time":0.3791415478},
{"learn":[3.912769674],"iteration":501,"passed_time":0.3810716964,"remaining_time":0.3780352685},
{"learn":[3.909373788],"iteration":502,"passed_time":0.381483311,"remaining_time":0.3769328142},
{"learn":[3.906706036],"iteration":503,"passed_time":0.3818960866,"remaining_time":0.375834244},
{"learn":[3.903895664],"iteration":504,"passed_time":0.3823871152,"remaining_time":0.3748150932},
{"learn":[3.902982967],"iteration":505,"passed_time":0.3829113671,"remaining_time":0.3738304651},
{"learn":[3.900905528],"iteration":506,"passed_time":0.3834135712,"remaining_time":0.3728262142},
{"learn":[3.897463465],"iteration":507,"passed_time":0.3839071348,"remaining_time":0.3718155715},
{"learn":[3.895918033],"iteration":508,"passed_time":0.3843809219,"remaining_time":0.3707878834},
{"learn":[3.893921936],"iteration":509,"passed_time":0.3849327966,"remaining_time":0.3698373928},
{"learn":[3.890237934],"iteration":510,"passed_time":0.3855242607,"remaining_time":0.3689263473},
{"learn":[3.887311613],"iteration":511,"passed_time":0.3859947423,"remaining_time":0.3679012387},
{"learn":[3.884869735],"iteration":512,"passed_time":0.3865512489,"remaining_time":0.3669599575},
{"learn":[3.882101231],"iteration":513,"passed_time":0.3870126041,"remaining_time":0.3659302054},
{"learn":[3.88060368],"iteration":514,"passed_time":0.3875072625,"remaining_time":0.3649340239},
{"learn":[3.877726076],"iteration":515,"passed_time":0.3879381601,"remaining_time":0.3638799796},
{"learn":[3.874938145],"iteration":516,"passed_time":0.3883586457,"remaining_time":0.3628186187},
{"learn":[3.874340833],"iteration":517,"passed_time":0.3887751947,"remaining_time":0.3617560692},
{"learn":[3.873105224],"iteration":518,"passed_time":0.3892176936,"remaining_time":0.360720059},
{"learn":[3.869800236],"iteration":519,"passed_time":0.3896714285,"remaining_time":0.3596967032},
{"learn":[3.867932518],"iteration":520,"passed_time":0.390116174,"remaining_time":0.3586672694},
{"learn":[3.866666962],"iteration":521,"passed_time":0.3905574574,"remaining_time":0.3576369054},
{"learn":[3.865527652],"iteration":522,"passed_time":0.3910653515,"remaining_time":0.3566695462},
{"learn":[3.861900081],"iteration":523,"passed_time":0.391618864,"remaining_time":0.3557453802},
{"learn":[3.858502887],"iteration":524,"passed_time":0.3920977433,"remaining_time":0.3547551011},
{"learn":[3.858335097],"iteration":525,"passed_time":0.3925821422,"remaining_time":0.3537717403},
{"learn":[3.855719306],"iteration":526,"passed_time":0.3931134243,"remaining_time":0.3528323524},
{"learn":[3.855137428],"iteration":527,"passed_time":0.3935822995,"remaining_time":0.3518387223},
{"learn":[3.851985706],"iteration":528,"passed_time":0.3940551925,"remaining_time":0.3508506534},
{"learn":[3.851051809],"iteration":529,"passed_time":0.394481576,"remaining_time":0.3498232844},
{"learn":[3.850679146],"iteration":530,"passed_time":0.3949150208,"remaining_time":0.3488044158},
{"learn":[3.848179484],"iteration":531,"passed_time":0.3953509669,"remaining_time":0.3477899484},
{"learn":[3.844551071],"iteration":532,"passed_time":0.3958168947,"remaining_time":0.3468039209},
{"learn":[3.841604794],"iteration":533,"passed_time":0.3962858803,"remaining_time":0.3458225097},
{"learn":[3.83969656],"iteration":534,"passed_time":0.3967574525,"remaining_time":0.3448452624},
{"learn":[3.836811463],"iteration":535,"passed_time":0.3973526448,"remaining_time":0.3439769164},
{"learn":[3.834182551],"iteration":536,"passed_time":0.3978878018,"remaining_time":0.3430578254},
{"learn":[3.828012842],"iteration":537,"passed_time":0.3984756,"remaining_time":0.3421853666},
{"learn":[3.826636176],"iteration":538,"passed_time":0.3989765439,"remaining_time":0.3412396786},
{"learn":[3.826189798],"iteration":539,"passed_time":0.3995534991,"remaining_time":0.3403603881},
{"learn":[3.824104738],"iteration":540,"passed_time":0.4001414505,"remaining_time":0.3394915449},
{"learn":[3.82300218],"iteration":541,"passed_time":0.4006801761,"remaining_time":0.3385821414},
{"learn":[3.817146402],"iteration":542,"passed_time":0.401181249,"remaining_time":0.337642414},
{"learn":[3.814638044],"iteration":543,"passed_time":0.4016904255,"remaining_time":0.336711092},
{"learn":[3.812979573],"iteration":544,"passed_time":0.4022665279,"remaining_time":0.335837193},
{"learn":[3.811938825],"iteration":545,"passed_time":0.4027221146,"remaining_time":0.3348641759},
{"learn":[3.811479418],"iteration":546,"passed_time":0.403180568,"remaining_time":0.3338954247},
{"learn":[3.80742981],"iteration":547,"passed_time":0.4036472513,"remaining_time":0.3329353241},
{"learn":[3.805097043],"iteration":548,"passed_time":0.4040978055,"remaining_time":0.331963771},
{"learn":[3.801577232],"iteration":549,"passed_time":0.4045253853,"remaining_time":0.3309753153},
{"learn":[3.799762083],"iteration":550,"passed_time":0.4049515184,"remaining_time":0.3299877165},
{"learn":[3.796393455],"iteration":551,"passed_time":0.4054276365,"remaining_time":0.3290427194},
{"learn":[3.793486459],"iteration":552,"passed_time":0.4058830692,"remaining_time":0.3280826979},
{"learn":[3.792006091],"iteration":553,"passed_time":0.4063045865,"remaining_time":0.3270971942},
{"learn":[3.78932128],"iteration":554,"passed_time":0.4067412548,"remaining_time":0.326125871},
{"learn":[3.787581812],"iteration":555,"passed_time":0.4071441087,"remaining_time":0.3251294681},
{"learn":[3.785308865],"iteration":556,"passed_time":0.4075518564,"remaining_time":0.3241390887},
{"learn":[3.78465475],"iteration":557,"passed_time":0.4079792885,"remaining_time":0.3231663898},
{"learn":[3.780498869],"iteration":558,"passed_time":0.4084190547,"remaining_time":0.3222053723},
{"learn":[3.778734909],"iteration":559,"passed_time":0.4088078106,"remaining_time":0.3212061369},
{"learn":[3.778652349],"iteration":560,"passed_time":0.4092029032,"remaining_time":0.3202140365},
{"learn":[3.777928006],"iteration":561,"passed_time":0.4095913496,"remaining_time":0.319218881},
{"learn":[3.776131406],"iteration":562,"passed_time":0.4100298392,"remaining_time":0.3182647242},
{"learn":[3.772925617],"iteration":563,"passed_time":0.4104386186,"remaining_time":0.3172894285},
{"learn":[3.7727745],"iteration":564,"passed_time":0.4108541544,"remaining_time":0.3163213401},
{"learn":[3.771763073],"iteration":565,"passed_time":0.4112674738,"remaining_time":0.3153535047},
{"learn":[3.768738162],"iteration":566,"passed_time":0.4116712153,"remaining_time":0.3143803108},
{"learn":[3.767220794],"iteration":567,"passed_time":0.4121974473,"remaining_time":0.3135022839},
{"learn":[3.766691102],"iteration":568,"passed_time":0.4127298215,"remaining_time":0.312630146},
{"learn":[3.766259335],"iteration":569,"passed_time":0.4132530471,"remaining_time":0.3117522987},
{"learn":[3.76116362],"iteration":570,"passed_time":0.4136926065,"remaining_time":0.310812834},
{"learn":[3.758633056],"iteration":571,"passed_time":0.4141989804,"remaining_time":0.3099251112},
{"learn":[3.754603809],"iteration":572,"passed_time":0.4146915829,"remaining_time":0.309028457},
{"learn":[3.754070549],"iteration":573,"passed_time":0.4151600959,"remaining_time":0.3081153325},
{"learn":[3.750534319],"iteration":574,"passed_time":0.4157092268,"remaining_time":0.3072633415},
{"learn":[3.746491516],"iteration":575,"passed_time":0.4162092723,"remaining_time":0.3063762699},
{"learn":[3.744210544],"iteration":576,"passed_time":0.4166582626,"remaining_time":0.3054531111},
{"learn":[3.742929991],"iteration":577,"passed_time":0.4171102406,"remaining_time":0.3045337743},
{"learn":[3.740402992],"iteration":578,"passed_time":0.4175134751,"remaining_time":0.3035806097},
{"learn":[3.739644243],"iteration":579,"passed_time":0.417896909,"remaining_time":0.3026150031},
{"learn":[3.737529404],"iteration":580,"passed_time":0.4183227419,"remaining_time":0.3016819774},
{"learn":[3.737196923],"iteration":581,"passed_time":0.4187276793,"remaining_time":0.3007356872},
{"learn":[3.733954464],"iteration":582,"passed_time":0.4191531354,"remaining_time":0.2998059304},
{"learn":[3.731608623],"iteration":583,"passed_time":0.4195762571,"remaining_time":0.2988762379},
{"learn":[3.729843952],"iteration":584,"passed_time":0.4200325178,"remaining_time":0.2979717861},
{"learn":[3.727223798],"iteration":585,"passed_time":0.4204928065,"remaining_time":0.2970717097},
{"learn":[3.725351667],"iteration":586,"passed_time":0.4210813611,"remaining_time":0.2962633767},
{"learn":[3.725026912],"iteration":587,"passed_time":0.4215722208,"remaining_time":0.2953873384},
{"learn":[3.721974565],"iteration":588,"passed_time":0.422018997,"remaining_time":0.2944818468},
{"learn":[3.720269493],"iteration":589,"passed_time":0.4224332033,"remaining_time":0.2935552769},
{"learn":[3.718907466],"iteration":590,"passed_time":0.4228450707,"remaining_time":0.2926288222},
{"learn":[3.715602912],"iteration":591,"passed_time":0.4232527189,"remaining_time":0.2917011981},
{"learn":[3.714463059],"iteration":592,"passed_time":0.4236770338,"remaining_time":0.2907867669},
{"learn":[3.710802077],"iteration":593,"passed_time":0.4241690665,"remaining_time":0.289920271},
{"learn":[3.708032435],"iteration":594,"passed_time":0.4246356732,"remaining_time":0.2890377271},
{"learn":[3.703788939],"iteration":595,"passed_time":0.4250713314,"remaining_time":0.2881356005},
{"learn":[3.702500944],"iteration":596,"passed_time":0.4255508965,"remaining_time":0.2872646756},
{"learn":[3.698196925],"iteration":597,"passed_time":0.4260205208,"remaining_time":0.2863883768},
{"learn":[3.69658891],"iteration":598,"passed_time":0.4265365465,"remaining_time":0.2855444994},
{"learn":[3.696124066],"iteration":599,"passed_time":0.4271345514,"remaining_time":0.2847563676},
{"learn":[3.693537052],"iteration":600,"passed_time":0.427752017,"remaining_time":0.2839817883},
{"learn":[3.691343275],"iteration":601,"passed_time":0.4282537378,"remaining_time":0.2831312087},
{"learn":[3.690973831],"iteration":602,"passed_time":0.4287157861,"remaining_time":0.2822556668},
{"learn":[3.686151073],"iteration":603,"passed_time":0.429218269,"remaining_time":0.2814080042},
{"learn":[3.683921982],"iteration":604,"passed_time":0.4298073835,"remaining_time":0.2806180437},
{"learn":[3.679975271],"iteration":605,"passed_time":0.4302993411,"remaining_time":0.2797655782},
{"learn":[3.674047638],"iteration":606,"passed_time":0.4307865894,"remaining_time":0.2789112514},
{"learn":[3.673151794],"iteration":607,"passed_time":0.4312628326,"remaining_time":0.2780510368},
{"learn":[3.670953108],"iteration":608,"passed_time":0.4317443423,"remaining_time":0.2771954644},
{"learn":[3.6703947],"iteration":609,"passed_time":0.4322406094,"remaining_time":0.2763505536},
{"learn":[3.668433805],"iteration":610,"passed_time":0.4326733313,"remaining_time":0.2754663271},
{"learn":[3.668304956],"iteration":611,"passed_time":0.4330973046,"remaining_time":0.2745780297},
{"learn":[3.667880012],"iteration":612,"passed_time":0.4335704174,"remaining_time":0.27372227},
{"learn":[3.667282264],"iteration":613,"passed_time":0.4340175919,"remaining_time":0.2728514503},
{"learn":[3.664611483],"iteration":614,"passed_time":0.4345025893,"remaining_time":0.272005686},
{"learn":[3.662543394],"iteration":615,"passed_time":0.4349385775,"remaining_time":0.2711305418},
{"learn":[3.659041959],"iteration":616,"passed_time":0.4353857152,"remaining_time":0.2702637422},
{"learn":[3.656868545],"iteration":617,"passed_time":0.435804012,"remaining_time":0.2693804735},
{"learn":[3.654785614],"iteration":618,"passed_time":0.4362606196,"remaining_time":0.2685222877},
{"learn":[3.654566096],"iteration":619,"passed_time":0.4366842116,"remaining_time":0.2676451619},
{"learn":[3.651007045],"iteration":620,"passed_time":0.4370686901,"remaining_time":0.2667456257},
{"learn":[3.648921786],"iteration":621,"passed_time":0.4375030088,"remaining_time":0.2658780343},
{"learn":[3.647655706],"iteration":622,"passed_time":0.4378840118,"remaining_time":0.2649795705},
{"learn":[3.647241144],"iteration":623,"passed_time":0.4383031533,"remaining_time":0.2641057462},
{"learn":[3.644195689],"iteration":624,"passed_time":0.4387440592,"remaining_time":0.2632464355},
{"learn":[3.642632246],"iteration":625,"passed_time":0.4391417756,"remaining_time":0.2623626583},
{"learn":[3.642523322],"iteration":626,"passed_time":0.4394364381,"remaining_time":0.2614191251},
{"learn":[3.641494659],"iteration":627,"passed_time":0.4398531603,"remaining_time":0.2605499612},
{"learn":[3.63976496],"iteration":628,"passed_time":0.4402357609,"remaining_time":0.2596621102},
{"learn":[3.637945652],"iteration":629,"passed_time":0.4408639524,"remaining_time":0.258920099},
{"learn":[3.636233667],"iteration":630,"passed_time":0.4413098777,"remaining_time":0.2580718619},
{"learn":[3.635304404],"iteration":631,"passed_time":0.4417824482,"remaining_time":0.2572404129},
{"learn":[3.632234951],"iteration":632,"passed_time":0.4423510337,"remaining_time":0.2564657652},
{"learn":[3.631630987],"iteration":633,"passed_time":0.4428415664,"remaining_time":0.2556467087},
{"learn":[3.630301009],"iteration":634,"passed_time":0.4432622236,"remaining_time":0.2547885222},
{"learn":[3.629077964],"iteration":635,"passed_time":0.443767933,"remaining_time":0.2539803894},
{"learn":[3.628004522],"iteration":636,"passed_time":0.4442612114,"remaining_time":0.253166122},
{"learn":[3.625062876],"iteration":637,"passed_time":0.4448663144,"remaining_time":0.25241631},
{"learn":[3.624917986],"iteration":638,"passed_time":0.4453505172,"remaining_time":0.251598649},
{"learn":[3.622887087],"iteration":639,"passed_time":0.4458356012,"remaining_time":0.2507825257},
{"learn":[3.621220865],"iteration":640,"passed_time":0.4462945547,"remaining_time":0.2499528005},
{"learn":[3.621143844],"iteration":641,"passed_time":0.44669428,"remaining_time":0.2490912029},
{"learn":[3.620822821],"iteration":642,"passed_time":0.4471236519,"remaining_time":0.2482475019},
{"learn":[3.619202826],"iteration":643,"passed_time":0.4475537147,"remaining_time":0.2474054696},
{"learn":[3.618204882],"iteration":644,"passed_time":0.4479580367,"remaining_time":0.2465505474},
{"learn":[3.614259666],"iteration":645,"passed_time":0.4483793579,"remaining_time":0.2457063355},
{"learn":[3.613415661],"iteration":646,"passed_time":0.4488273128,"remaining_time":0.244877962},
{"learn":[3.611096773],"iteration":647,"passed_time":0.449257155,"remaining_time":0.2440409237},
{"learn":[3.610820695],"iteration":648,"passed_time":0.4496469693,"remaining_time":0.2431834918},
{"learn":[3.609290065],"iteration":649,"passed_time":0.4500669624,"remaining_time":0.242343749},
{"learn":[3.60897947],"iteration":650,"passed_time":0.4504428326,"remaining_time":0.2414816414},
{"learn":[3.606570702],"iteration":651,"passed_time":0.4508338554,"remaining_time":0.240629113},
{"learn":[3.606292637],"iteration":652,"passed_time":0.4512128656,"remaining_time":0.2397716147},
{"learn":[3.602753838],"iteration":653,"passed_time":0.4516402272,"remaining_time":0.23894116},
{"learn":[3.599755869],"iteration":654,"passed_time":0.4520465635,"remaining_time":0.2381008617},
{"learn":[3.599509575],"iteration":655,"passed_time":0.4524771746,"remaining_time":0.2372746159},
{"learn":[3.595337722],"iteration":656,"passed_time":0.4529045913,"remaining_time":0.2364479069},
{"learn":[3.595168561],"iteration":657,"passed_time":0.4533255211,"remaining_time":0.2356190398},
{"learn":[3.59290559],"iteration":658,"passed_time":0.4537225452,"remaining_time":0.2347790408},
{"learn":[3.592015928],"iteration":659,"passed_time":0.4541021497,"remaining_time":0.2339314105},
{"learn":[3.590680403],"iteration":660,"passed_time":0.454546309,"remaining_time":0.2331183037},
{"learn":[3.590361532],"iteration":661,"passed_time":0.4549390841,"remaining_time":0.2322800762},
{"learn":[3.589069739],"iteration":662,"passed_time":0.4553320292,"remaining_time":0.2314432788},
{"learn":[3.585010186],"iteration":663,"passed_time":0.4557326062,"remaining_time":0.2306116803},
{"learn":[3.582997552],"iteration":664,"passed_time":0.4562404107,"remaining_time":0.2298353949},
{"learn":[3.582119256],"iteration":665,"passed_time":0.4567542564,"remaining_time":0.2290629454},
{"learn":[3.579019356],"iteration":666,"passed_time":0.4572341416,"remaining_time":0.2282743166},
{"learn":[3.57719559],"iteration":667,"passed_time":0.457786969,"remaining_time":0.2275228648},
{"learn":[3.574050046],"iteration":668,"passed_time":0.4582928531,"remaining_time":0.2267487808},
{"learn":[3.572204518],"iteration":669,"passed_time":0.4588821441,"remaining_time":0.2260165784},
{"learn":[3.569508025],"iteration":670,"passed_time":0.4594354451,"remaining_time":0.2252671557},
{"learn":[3.566268704],"iteration":671,"passed_time":0.4599314526,"remaining_time":0.2244903519},
{"learn":[3.562564052],"iteration":672,"passed_time":0.4607155707,"remaining_time":0.2238543709},
{"learn":[3.561173586],"iteration":673,"passed_time":0.4612478044,"remaining_time":0.223096119},
{"learn":[3.559551904],"iteration":674,"passed_time":0.4616697375,"remaining_time":0.2222854291},
{"learn":[3.558593054],"iteration":675,"passed_time":0.4621130749,"remaining_time":0.2214861483},
{"learn":[3.555647008],"iteration":676,"passed_time":0.4625361668,"remaining_time":0.2206782598},
{"learn":[3.553100059],"iteration":677,"passed_time":0.4629711747,"remaining_time":0.2198771656},
{"learn":[3.55085578],"iteration":678,"passed_time":0.4634168243,"remaining_time":0.2190821806},
{"learn":[3.550737965],"iteration":679,"passed_time":0.4638433128,"remaining_time":0.218279206},
{"learn":[3.549408772],"iteration":680,"passed_time":0.4642892443,"remaining_time":0.2174864448},
{"learn":[3.547390589],"iteration":681,"passed_time":0.4647550545,"remaining_time":0.2167039697},
{"learn":[3.54723575],"iteration":682,"passed_time":0.4652750152,"remaining_time":0.2159475546},
{"learn":[3.543988891],"iteration":683,"passed_time":0.4658990121,"remaining_time":0.2152398945},
{"learn":[3.543868508],"iteration":684,"passed_time":0.4664126203,"remaining_time":0.2144817159},
{"learn":[3.542752124],"iteration":685,"passed_time":0.4669126057,"remaining_time":0.2137180148},
{"learn":[3.541334315],"iteration":686,"passed_time":0.467414312,"remaining_time":0.2129558656},
{"learn":[3.540208266],"iteration":687,"passed_time":0.4678819557,"remaining_time":0.2121790264},
{"learn":[3.537730983],"iteration":688,"passed_time":0.4683517967,"remaining_time":0.2114040766},
{"learn":[3.53419867],"iteration":689,"passed_time":0.4688592493,"remaining_time":0.2106469091},
{"learn":[3.532628335],"iteration":690,"passed_time":0.4693291569,"remaining_time":0.2098736751},
{"learn":[3.532204987],"iteration":691,"passed_time":0.4698160759,"remaining_time":0.2091088893},
{"learn":[3.530618147],"iteration":692,"passed_time":0.4702741586,"remaining_time":0.2083321309},
{"learn":[3.528909306],"iteration":693,"passed_time":0.4707231428,"remaining_time":0.2075522791},
{"learn":[3.526700678],"iteration":694,"passed_time":0.4711982943,"remaining_time":0.2067848629},
{"learn":[3.526439574],"iteration":695,"passed_time":0.4717118799,"remaining_time":0.206035074},
{"learn":[3.525784216],"iteration":696,"passed_time":0.4723023797,"remaining_time":0.2053193989},
{"learn":[3.524112693],"iteration":697,"passed_time":0.4729165689,"remaining_time":0.2046143321},
{"learn":[3.522813541],"iteration":698,"passed_time":0.4735282802,"remaining_time":0.2039084583},
{"learn":[3.519148203],"iteration":699,"passed_time":0.4740554396,"remaining_time":0.203166617},
{"learn":[3.517236747],"iteration":700,"passed_time":0.4746422151,"remaining_time":0.2024508164},
{"learn":[3.515603888],"iteration":701,"passed_time":0.4752055696,"remaining_time":0.2017254412},
{"learn":[3.51263524],"iteration":702,"passed_time":0.4757241587,"remaining_time":0.2009816147},
{"learn":[3.51123442],"iteration":703,"passed_time":0.4762605785,"remaining_time":0.2002459251},
{"learn":[3.50828027],"iteration":704,"passed_time":0.4767047546,"remaining_time":0.1994722023},
{"learn":[3.508265537],"iteration":705,"passed_time":0.4769765661,"remaining_time":0.1986276352},
{"learn":[3.506774876],"iteration":706,"passed_time":0.4774451595,"remaining_time":0.1978662401},
{"learn":[3.50552068],"iteration":707,"passed_time":0.4778628726,"remaining_time":0.1970846876},
{"learn":[3.501973993],"iteration":708,"passed_time":0.4782841854,"remaining_time":0.1963056389},
{"learn":[3.498880354],"iteration":709,"passed_time":0.4787593683,"remaining_time":0.1955496011},
{"learn":[3.497370959],"iteration":710,"passed_time":0.4791994125,"remaining_time":0.1947800706},
{"learn":[3.496050455],"iteration":711,"passed_time":0.479626176,"remaining_time":0.1940060936},
{"learn":[3.495630067],"iteration":712,"passed_time":0.4800314775,"remaining_time":0.1932244517},
{"learn":[3.49550669],"iteration":713,"passed_time":0.4804279702,"remaining_time":0.1924403354},
{"learn":[3.493652375],"iteration":714,"passed_time":0.4808713429,"remaining_time":0.1916759898},
{"learn":[3.491915684],"iteration":715,"passed_time":0.4812833634,"remaining_time":0.190900105},
{"learn":[3.490303956],"iteration":716,"passed_time":0.4817186286,"remaining_time":0.1901344099},
{"learn":[3.488363853],"iteration":717,"passed_time":0.4821184061,"remaining_time":0.1893556971},
{"learn":[3.485483936],"iteration":718,"passed_time":0.4825207315,"remaining_time":0.1885790341},
{"learn":[3.483763466],"iteration":719,"passed_time":0.4829242609,"remaining_time":0.1878038792},
{"learn":[3.481642352],"iteration":720,"passed_time":0.4833466619,"remaining_time":0.1870370578},
{"learn":[3.479826119],"iteration":721,"passed_time":0.4837484038,"remaining_time":0.1862632358},
{"learn":[3.478588728],"iteration":722,"passed_time":0.4841892752,"remaining_time":0.1855054346},
{"learn":[3.475390887],"iteration":723,"passed_time":0.4846275411,"remaining_time":0.1847475157},
{"learn":[3.472636852],"iteration":724,"passed_time":0.4850595062,"remaining_time":0.1839880886},
{"learn":[3.47061883],"iteration":725,"passed_time":0.485480963,"remaining_time":0.1832255976},
{"learn":[3.46953149],"iteration":726,"passed_time":0.4858601547,"remaining_time":0.1824481736},
{"learn":[3.467217162],"iteration":727,"passed_time":0.4864324672,"remaining_time":0.1817439987},
{"learn":[3.465686216],"iteration":728,"passed_time":0.4869627648,"remaining_time":0.1810245669},
{"learn":[3.462631216],"iteration":729,"passed_time":0.4875180483,"remaining_time":0.1803148946},
{"learn":[3.461451053],"iteration":730,"passed_time":0.4880898986,"remaining_time":0.1796117411},
{"learn":[3.458950469],"iteration":731,"passed_time":0.4886383571,"remaining_time":0.1789003821},
{"learn":[3.458072145],"iteration":732,"passed_time":0.4891799795,"remaining_time":0.1781869775},
{"learn":[3.454364268],"iteration":733,"passed_time":0.4896825569,"remaining_time":0.1774598912},
{"learn":[3.453243406],"iteration":734,"passed_time":0.4901996414,"remaining_time":0.1767386462},
{"learn":[3.453017963],"iteration":735,"passed_time":0.4906608473,"remaining_time":0.1759979126},
{"learn":[3.45201581],"iteration":736,"passed_time":0.4911244817,"remaining_time":0.1752588042},
{"learn":[3.449510107],"iteration":737,"passed_time":0.4915887947,"remaining_time":0.1745206832},
{"learn":[3.447189189],"iteration":738,"passed_time":0.49200479,"remaining_time":0.1737662384},
{"learn":[3.446423605],"iteration":739,"passed_time":0.4924165908,"remaining_time":0.1730112346},
{"learn":[3.445531987],"iteration":740,"passed_time":0.49281018,"remaining_time":0.1722507917},
{"learn":[3.445328199],"iteration":741,"passed_time":0.4932191026,"remaining_time":0.1714966691},
{"learn":[3.443327544],"iteration":742,"passed_time":0.4936307294,"remaining_time":0.1707444111},
{"learn":[3.441475798],"iteration":743,"passed_time":0.4940435464,"remaining_time":0.1699934783},
{"learn":[3.439046501],"iteration":744,"passed_time":0.4944666804,"remaining_time":0.1692469846},
{"learn":[3.435899469],"iteration":745,"passed_time":0.4948822814,"remaining_time":0.1684987928},
{"learn":[3.433988352],"iteration":746,"passed_time":0.4953705709,"remaining_time":0.1677761103},
{"learn":[3.433413263],"iteration":747,"passed_time":0.4958690452,"remaining_time":0.1670574858},
{"learn":[3.429944699],"iteration":748,"passed_time":0.4963887091,"remaining_time":0.1663465501},
{"learn":[3.429291634],"iteration":749,"passed_time":0.496829772,"remaining_time":0.165609924},
{"learn":[3.429175603],"iteration":750,"passed_time":0.4972446591,"remaining_time":0.1648654063},
{"learn":[3.428780323],"iteration":751,"passed_time":0.4976502617,"remaining_time":0.1641187033},
{"learn":[3.423893341],"iteration":752,"passed_time":0.4980827362,"remaining_time":0.1633817209},
{"learn":[3.421024316],"iteration":753,"passed_time":0.4984949543,"remaining_time":0.1626389373},
{"learn":[3.420969872],"iteration":754,"passed_time":0.4989020978,"remaining_time":0.1618953827},
{"learn":[3.419544785],"iteration":755,"passed_time":0.4993292816,"remaining_time":0.1611591861},
{"learn":[3.417057977],"iteration":756,"passed_time":0.4997716488,"remaining_time":0.1604286799},
{"learn":[3.415160245],"iteration":757,"passed_time":0.5001915837,"remaining_time":0.1596917721},
{"learn":[3.412854597],"iteration":758,"passed_time":0.5006655049,"remaining_time":0.1589728415},
{"learn":[3.410926347],"iteration":759,"passed_time":0.5012458938,"remaining_time":0.158288177},
{"learn":[3.408963843],"iteration":760,"passed_time":0.5017876433,"remaining_time":0.1575916514},
{"learn":[3.407629634],"iteration":761,"passed_time":0.5024013853,"remaining_time":0.156918018},
{"learn":[3.404384724],"iteration":762,"passed_time":0.5028950998,"remaining_time":0.156207259},
{"learn":[3.403041656],"iteration":763,"passed_time":0.5033874824,"remaining_time":0.1554966569},
{"learn":[3.401101731],"iteration":764,"passed_time":0.503907028,"remaining_time":0.1547949694},
{"learn":[3.400890668],"iteration":765,"passed_time":0.5044362576,"remaining_time":0.1540967158},
{"learn":[3.399289941],"iteration":766,"passed_time":0.5049182582,"remaining_time":0.1533845556},
{"learn":[3.399202366],"iteration":767,"passed_time":0.5053558601,"remaining_time":0.1526595827},
{"learn":[3.397447845],"iteration":768,"passed_time":0.5057767187,"remaining_time":0.1519303277},
{"learn":[3.394655341],"iteration":769,"passed_time":0.5061730099,"remaining_time":0.1511945354},
{"learn":[3.393228229],"iteration":770,"passed_time":0.5065953788,"remaining_time":0.1504673693},
{"learn":[3.389691197],"iteration":771,"passed_time":0.5070094319,"remaining_time":0.1497385369},
{"learn":[3.389626772],"iteration":772,"passed_time":0.5074262199,"remaining_time":0.149011322},
{"learn":[3.388480222],"iteration":773,"passed_time":0.507878904,"remaining_time":0.1482953906},
{"learn":[3.388215066],"iteration":774,"passed_time":0.5083218815,"remaining_time":0.1475773204},
{"learn":[3.386324358],"iteration":775,"passed_time":0.5089300717,"remaining_time":0.1469076496},
{"learn":[3.383913061],"iteration":776,"passed_time":0.5094686414,"remaining_time":0.1462181558},
{"learn":[3.382839768],"iteration":777,"passed_time":0.5099223448,"remaining_time":0.1455048336},
{"learn":[3.381961844],"iteration":778,"passed_time":0.5104132126,"remaining_time":0.1448027214},
{"learn":[3.381521703],"iteration":779,"passed_time":0.5108709246,"remaining_time":0.1440917993},
{"learn":[3.380918963],"iteration":780,"passed_time":0.5113520958,"remaining_time":0.1433881037},
{"learn":[3.377139006],"iteration":781,"passed_time":0.5118272687,"remaining_time":0.1426833051},
{"learn":[3.376004372],"iteration":782,"passed_time":0.5122740572,"remaining_time":0.1419712266},
{"learn":[3.373826468],"iteration":783,"passed_time":0.5127299939,"remaining_time":0.1412623453},
{"learn":[3.373546786],"iteration":784,"passed_time":0.5131758511,"remaining_time":0.1405513477},
{"learn":[3.372109181],"iteration":785,"passed_time":0.5136441833,"remaining_time":0.1398471441},
{"learn":[3.370764924],"iteration":786,"passed_time":0.5141014097,"remaining_time":0.139140534},
{"learn":[3.367833107],"iteration":787,"passed_time":0.5145044191,"remaining_time":0.1384199706},
{"learn":[3.36450404],"iteration":788,"passed_time":0.5150500236,"remaining_time":0.137738346},
{"learn":[3.361794558],"iteration":789,"passed_time":0.515512991,"remaining_time":0.1370350989},
{"learn":[3.356880529],"iteration":790,"passed_time":0.5159790363,"remaining_time":0.1363332726},
{"learn":[3.353843509],"iteration":791,"passed_time":0.5165399436,"remaining_time":0.1356569549},
{"learn":[3.353640253],"iteration":792,"passed_time":0.5170445131,"remaining_time":0.1349662222},
{"learn":[3.353055088],"iteration":793,"passed_time":0.5175191989,"remaining_time":0.1342682053},
{"learn":[3.351415617],"iteration":794,"passed_time":0.518031118,"remaining_time":0.1335803512},
{"learn":[3.349169061],"iteration":795,"passed_time":0.518630611,"remaining_time":0.1329153827},
{"learn":[3.346211014],"iteration":796,"passed_time":0.5191881289,"remaining_time":0.1322398873},
{"learn":[3.344560452],"iteration":797,"passed_time":0.5196968169,"remaining_time":0.1315523271},
{"learn":[3.344445461],"iteration":798,"passed_time":0.5201653494,"remaining_time":0.1308551129},
{"learn":[3.342608898],"iteration":799,"passed_time":0.5205938299,"remaining_time":0.1301484575},
{"learn":[3.339572899],"iteration":800,"passed_time":0.5210381522,"remaining_time":0.1294464323},
{"learn":[3.339309302],"iteration":801,"passed_time":0.5214603296,"remaining_time":0.1287395826},
{"learn":[3.33698088],"iteration":802,"passed_time":0.5218770457,"remaining_time":0.1280321021},
{"learn":[3.334746342],"iteration":803,"passed_time":0.5223184601,"remaining_time":0.1273313659},
{"learn":[3.332048511],"iteration":804,"passed_time":0.5227352879,"remaining_time":0.1266253182},
{"learn":[3.331932544],"iteration":805,"passed_time":0.523149845,"remaining_time":0.1259194416},
{"learn":[3.330541133],"iteration":806,"passed_time":0.5235829099,"remaining_time":0.1252187133},
{"learn":[3.329124989],"iteration":807,"passed_time":0.5239813249,"remaining_time":0.1245104138},
{"learn":[3.32583918],"iteration":808,"passed_time":0.5244382304,"remaining_time":0.1238166897},
{"learn":[3.325287299],"iteration":809,"passed_time":0.5248553002,"remaining_time":0.1231142062},
{"learn":[3.322745162],"iteration":810,"passed_time":0.5252898265,"remaining_time":0.1224164947},
{"learn":[3.319733662],"iteration":811,"passed_time":0.5258185379,"remaining_time":0.1217412378},
{"learn":[3.318080007],"iteration":812,"passed_time":0.526331862,"remaining_time":0.1210628022},
{"learn":[3.317179538],"iteration":813,"passed_time":0.526905275,"remaining_time":0.1203985027},
{"learn":[3.315685949],"iteration":814,"passed_time":0.5273688995,"remaining_time":0.1197095048},
{"learn":[3.314944576],"iteration":815,"passed_time":0.5278161965,"remaining_time":0.1190173776},
{"learn":[3.312369052],"iteration":816,"passed_time":0.5282819214,"remaining_time":0.1183299775},
{"learn":[3.312321621],"iteration":817,"passed_time":0.5286088275,"remaining_time":0.117612233},
{"learn":[3.309465776],"iteration":818,"passed_time":0.5290582743,"remaining_time":0.1169225246},
{"learn":[3.308307377],"iteration":819,"passed_time":0.5294614521,"remaining_time":0.1162232456},
{"learn":[3.308076804],"iteration":820,"passed_time":0.5298301224,"remaining_time":0.1155171643},
{"learn":[3.305643326],"iteration":821,"passed_time":0.5302431256,"remaining_time":0.1148215041},
{"learn":[3.304154814],"iteration":822,"passed_time":0.5306662856,"remaining_time":0.1141287151},
{"learn":[3.303076321],"iteration":823,"passed_time":0.5311264476,"remaining_time":0.1134444839},
{"learn":[3.301746372],"iteration":824,"passed_time":0.531723427,"remaining_time":0.1127898179},
{"learn":[3.301345455],"iteration":825,"passed_time":0.532354667,"remaining_time":0.1121425086},
{"learn":[3.299181039],"iteration":826,"passed_time":0.532926571,"remaining_time":0.1114828256},
{"learn":[3.297989357],"iteration":827,"passed_time":0.5334124943,"remaining_time":0.110805494},
{"learn":[3.294775182],"iteration":828,"passed_time":0.5339322352,"remaining_time":0.1101355998},
{"learn":[3.293840636],"iteration":829,"passed_time":0.5344876068,"remaining_time":0.1094733652},
{"learn":[3.289279397],"iteration":830,"passed_time":0.5350125272,"remaining_time":0.1088051951},
{"learn":[3.286204979],"iteration":831,"passed_time":0.5355188352,"remaining_time":0.108133611},
{"learn":[3.284833593],"iteration":832,"passed_time":0.5359735795,"remaining_time":0.1074520862},
{"learn":[3.283519914],"iteration":833,"passed_time":0.5363962325,"remaining_time":0.1067647177},
{"learn":[3.282853026],"iteration":834,"passed_time":0.5368432132,"remaining_time":0.1060827906},
{"learn":[3.281944673],"iteration":835,"passed_time":0.5372840899,"remaining_time":0.1054002282},
{"learn":[3.279764865],"iteration":836,"passed_time":0.5377252118,"remaining_time":0.1047182909},
{"learn":[3.277468839],"iteration":837,"passed_time":0.5381729959,"remaining_time":0.1040382164},
{"learn":[3.277124974],"iteration":838,"passed_time":0.5386196786,"remaining_time":0.1033584842},
{"learn":[3.275636037],"iteration":839,"passed_time":0.5391128015,"remaining_time":0.1026881527},
{"learn":[3.274413635],"iteration":840,"passed_time":0.5395407804,"remaining_time":0.1020059264},
{"learn":[3.272636087],"iteration":841,"passed_time":0.5399785033,"remaining_time":0.1013261324},
{"learn":[3.269644466],"iteration":842,"passed_time":0.5404492488,"remaining_time":0.1006530629},
{"learn":[3.26852083],"iteration":843,"passed_time":0.5409050109,"remaining_time":0.09997770343},
{"learn":[3.267820927],"iteration":844,"passed_time":0.5413580832,"remaining_time":0.0993023703},
{"learn":[3.267331099],"iteration":845,"passed_time":0.5417811835,"remaining_time":0.09862210669},
{"learn":[3.267231014],"iteration":846,"passed_time":0.5422764435,"remaining_time":0.09795548508},
{"learn":[3.267158695],"iteration":847,"passed_time":0.5427047923,"remaining_time":0.09727727409},
{"learn":[3.264718705],"iteration":848,"passed_time":0.5431265316,"remaining_time":0.09659847618},
{"learn":[3.261678512],"iteration":849,"passed_time":0.5435648642,"remaining_time":0.09592321133},
{"learn":[3.261368381],"iteration":850,"passed_time":0.5439934427,"remaining_time":0.09524679549},
{"learn":[3.260128799],"iteration":851,"passed_time":0.5444533282,"remaining_time":0.09457639973},
{"learn":[3.258972952],"iteration":852,"passed_time":0.5448852796,"remaining_time":0.09390168358},
{"learn":[3.258724846],"iteration":853,"passed_time":0.5453329817,"remaining_time":0.09323022872},
{"learn":[3.25686724],"iteration":854,"passed_time":0.5457716375,"remaining_time":0.09255776308},
{"learn":[3.255750259],"iteration":855,"passed_time":0.546336343,"remaining_time":0.09190704836},
{"learn":[3.254915866],"iteration":856,"passed_time":0.5469241179,"remaining_time":0.09126038374},
{"learn":[3.254348625],"iteration":857,"passed_time":0.5474516641,"remaining_time":0.09060388847},
{"learn":[3.253408514],"iteration":858,"passed_time":0.5479329889,"remaining_time":0.08994010644},
{"learn":[3.253291714],"iteration":859,"passed_time":0.548450459,"remaining_time":0.08928263285},
{"learn":[3.250186342],"iteration":860,"passed_time":0.5490655752,"remaining_time":0.0886412485},
{"learn":[3.249141318],"iteration":861,"passed_time":0.5495443833,"remaining_time":0.08797810313},
{"learn":[3.246300388],"iteration":862,"passed_time":0.5500874666,"remaining_time":0.08732558856},
{"learn":[3.245205135],"iteration":863,"passed_time":0.5505860314,"remaining_time":0.08666631975},
{"learn":[3.244403535],"iteration":864,"passed_time":0.5510356612,"remaining_time":0.08599978527},
{"learn":[3.244211781],"iteration":865,"passed_time":0.551522005,"remaining_time":0.08533943264},
{"learn":[3.242286347],"iteration":866,"passed_time":0.5519658066,"remaining_time":0.08467295534},
{"learn":[3.239606746],"iteration":867,"passed_time":0.5523786014,"remaining_time":0.08400227579},
{"learn":[3.236773361],"iteration":868,"passed_time":0.5527951604,"remaining_time":0.08333275721},
{"learn":[3.234552446],"iteration":869,"passed_time":0.553219905,"remaining_time":0.08266504328},
{"learn":[3.233724647],"iteration":870,"passed_time":0.5536430352,"remaining_time":0.08199764815},
{"learn":[3.230851485],"iteration":871,"passed_time":0.5540556776,"remaining_time":0.08132927377},
{"learn":[3.227728941],"iteration":872,"passed_time":0.5544842178,"remaining_time":0.080663798},
{"learn":[3.225787575],"iteration":873,"passed_time":0.5549136418,"remaining_time":0.07999899184},
{"learn":[3.222797487],"iteration":874,"passed_time":0.5553933594,"remaining_time":0.07934190848},
{"learn":[3.22137014],"iteration":875,"passed_time":0.5559746777,"remaining_time":0.07869961191},
{"learn":[3.219701963],"iteration":876,"passed_time":0.5564533843,"remaining_time":0.07804306302},
{"learn":[3.21783327],"iteration":877,"passed_time":0.5569171007,"remaining_time":0.07738483631},
{"learn":[3.217713355],"iteration":878,"passed_time":0.5573105076,"remaining_time":0.07671737363},
{"learn":[3.217666091],"iteration":879,"passed_time":0.5576968541,"remaining_time":0.07604957101},
{"learn":[3.214962005],"iteration":880,"passed_time":0.5581309675,"remaining_time":0.0753888594},
{"learn":[3.214081828],"iteration":881,"passed_time":0.5585702099,"remaining_time":0.07472934781},
{"learn":[3.213358337],"iteration":882,"passed_time":0.5590307433,"remaining_time":0.07407315625},
{"learn":[3.210850401],"iteration":883,"passed_time":0.5595022914,"remaining_time":0.07341885272},
{"learn":[3.207810328],"iteration":884,"passed_time":0.5599712853,"remaining_time":0.0727646303},
{"learn":[3.204935073],"iteration":885,"passed_time":0.5604486555,"remaining_time":0.07211190376},
{"learn":[3.20280198],"iteration":886,"passed_time":0.5609979488,"remaining_time":0.07146873531},
{"learn":[3.200663495],"iteration":887,"passed_time":0.5616382421,"remaining_time":0.07083725576},
{"learn":[3.197301669],"iteration":888,"passed_time":0.562246072,"remaining_time":0.07020170303},
{"learn":[3.195666943],"iteration":889,"passed_time":0.5628283288,"remaining_time":0.06956305188},
{"learn":[3.193886506],"iteration":890,"passed_time":0.5634283871,"remaining_time":0.06892670504},
{"learn":[3.190601248],"iteration":891,"passed_time":0.5640666723,"remaining_time":0.06829506795},
{"learn":[3.188983797],"iteration":892,"passed_time":0.5646549243,"remaining_time":0.06765742095},
{"learn":[3.187365749],"iteration":893,"passed_time":0.565166701,"remaining_time":0.0670108169},
{"learn":[3.186160771],"iteration":894,"passed_time":0.5656769383,"remaining_time":0.06636433354},
{"learn":[3.185358981],"iteration":895,"passed_time":0.5661416725,"remaining_time":0.0657128727},
{"learn":[3.183832164],"iteration":896,"passed_time":0.5665965791,"remaining_time":0.06506069972},
{"learn":[3.183106966],"iteration":897,"passed_time":0.5670851393,"remaining_time":0.06441278866},
{"learn":[3.182838152],"iteration":898,"passed_time":0.5675632118,"remaining_time":0.06376405383},
{"learn":[3.180835453],"iteration":899,"passed_time":0.5680590363,"remaining_time":0.0631176707},
{"learn":[3.179957348],"iteration":900,"passed_time":0.5685543461,"remaining_time":0.06247156522},
{"learn":[3.179752966],"iteration":901,"passed_time":0.5690099941,"remaining_time":0.06182148495},
{"learn":[3.178851983],"iteration":902,"passed_time":0.5694439696,"remaining_time":0.06116950726},
{"learn":[3.176748586],"iteration":903,"passed_time":0.5698544692,"remaining_time":0.06051551885},
{"learn":[3.172960988],"iteration":904,"passed_time":0.5703899206,"remaining_time":0.05987518504},
{"learn":[3.172794225],"iteration":905,"passed_time":0.5708908404,"remaining_time":0.05923149999},
{"learn":[3.169996507],"iteration":906,"passed_time":0.5713260673,"remaining_time":0.05858139389},
{"learn":[3.16813015],"iteration":907,"passed_time":0.5717910221,"remaining_time":0.05793477316},
{"learn":[3.166920871],"iteration":908,"passed_time":0.5722109203,"remaining_time":0.05728404153},
{"learn":[3.16531606],"iteration":909,"passed_time":0.5726525736,"remaining_time":0.05663596882},
{"learn":[3.162035247],"iteration":910,"passed_time":0.5731248087,"remaining_time":0.05599133697},
{"learn":[3.16189467],"iteration":911,"passed_time":0.5735379566,"remaining_time":0.05534138178},
{"learn":[3.161008416],"iteration":912,"passed_time":0.5739516597,"remaining_time":0.05469199824},
{"learn":[3.160560787],"iteration":913,"passed_time":0.5743797833,"remaining_time":0.05404448727},
{"learn":[3.160416261],"iteration":914,"passed_time":0.5748342733,"remaining_time":0.05339990517},
{"learn":[3.15844291],"iteration":915,"passed_time":0.5752820781,"remaining_time":0.05275512506},
{"learn":[3.155040501],"iteration":916,"passed_time":0.5758724225,"remaining_time":0.05212367619},
{"learn":[3.154937548],"iteration":917,"passed_time":0.5765269838,"remaining_time":0.05149805302},
{"learn":[3.153721161],"iteration":918,"passed_time":0.5771199574,"remaining_time":0.05086693858},
{"learn":[3.153170511],"iteration":919,"passed_time":0.577729265,"remaining_time":0.05023732739},
{"learn":[3.153113601],"iteration":920,"passed_time":0.5783106813,"remaining_time":0.04960536789},
{"learn":[3.150607379],"iteration":921,"passed_time":0.5789503191,"remaining_time":0.04897844348},
{"learn":[3.148408359],"iteration":922,"passed_time":0.5795497213,"remaining_time":0.04834813493},
{"learn":[3.147495728],"iteration":923,"passed_time":0.5802111915,"remaining_time":0.04772299844},
{"learn":[3.146946235],"iteration":924,"passed_time":0.5807134746,"remaining_time":0.04708487631},
{"learn":[3.14472738],"iteration":925,"passed_time":0.5812203244,"remaining_time":0.04644741253},
{"learn":[3.144469477],"iteration":926,"passed_time":0.5816888473,"remaining_time":0.04580721236},
{"learn":[3.142975516],"iteration":927,"passed_time":0.5821167764,"remaining_time":0.04516423265},
{"learn":[3.14079113],"iteration":928,"passed_time":0.5825683906,"remaining_time":0.04452352608},
{"learn":[3.138173032],"iteration":929,"passed_time":0.583042852,"remaining_time":0.04388494585},
{"learn":[3.136352813],"iteration":930,"passed_time":0.5834888746,"remaining_time":0.04324461047},
{"learn":[3.133735004],"iteration":931,"passed_time":0.5839783478,"remaining_time":0.04260786228},
{"learn":[3.1319496],"iteration":932,"passed_time":0.5845189489,"remaining_time":0.04197510137},
{"learn":[3.129865343],"iteration":933,"passed_time":0.5850699129,"remaining_time":0.04134327008},
{"learn":[3.129830206],"iteration":934,"passed_time":0.5854708801,"remaining_time":0.04070118418},
{"learn":[3.126676562],"iteration":935,"passed_time":0.586025498,"remaining_time":0.04007011952},
{"learn":[3.12645665],"iteration":936,"passed_time":0.5865332026,"remaining_time":0.03943606378},
{"learn":[3.126378007],"iteration":937,"passed_time":0.5870053481,"remaining_time":0.03879992706},
{"learn":[3.124621914],"iteration":938,"passed_time":0.5874406723,"remaining_time":0.03816174762},
{"learn":[3.123379018],"iteration":939,"passed_time":0.5878690716,"remaining_time":0.03752355776},
{"learn":[3.123332451],"iteration":940,"passed_time":0.5882506582,"remaining_time":0.03688287868},
{"learn":[3.122432444],"iteration":941,"passed_time":0.5887172435,"remaining_time":0.03624798315},
{"learn":[3.121889006],"iteration":942,"passed_time":0.5891682013,"remaining_time":0.03561249997},
{"learn":[3.121070914],"iteration":943,"passed_time":0.5895874539,"remaining_time":0.03497552693},
{"learn":[3.118444705],"iteration":944,"passed_time":0.5900099246,"remaining_time":0.03433920196},
{"learn":[3.116820458],"iteration":945,"passed_time":0.59048446,"remaining_time":0.0337063011},
{"learn":[3.114971041],"iteration":946,"passed_time":0.5910532748,"remaining_time":0.03307901115},
{"learn":[3.114685138],"iteration":947,"passed_time":0.5915673081,"remaining_time":0.03244883968},
{"learn":[3.113399363],"iteration":948,"passed_time":0.5921933222,"remaining_time":0.03182493091},
{"learn":[3.110575399],"iteration":949,"passed_time":0.5927359176,"remaining_time":0.03119662724},
{"learn":[3.110466553],"iteration":950,"passed_time":0.5932694249,"remaining_time":0.03056803556},
{"learn":[3.108691641],"iteration":951,"passed_time":0.593843054,"remaining_time":0.02994166659},
{"learn":[3.107898017],"iteration":952,"passed_time":0.5943466569,"remaining_time":0.02931195475},
{"learn":[3.105551729],"iteration":953,"passed_time":0.5949550765,"remaining_time":0.02868756134},
{"learn":[3.104824945],"iteration":954,"passed_time":0.5954198543,"remaining_time":0.02805643293},
{"learn":[3.103186704],"iteration":955,"passed_time":0.595864176,"remaining_time":0.02742471103},
{"learn":[3.102330655],"iteration":956,"passed_time":0.5962733452,"remaining_time":0.0267918013},
{"learn":[3.102291298],"iteration":957,"passed_time":0.596688361,"remaining_time":0.02615961499},
{"learn":[3.100363529],"iteration":958,"passed_time":0.5971043732,"remaining_time":0.02552792419},
{"learn":[3.097871596],"iteration":959,"passed_time":0.597615706,"remaining_time":0.02490065442},
{"learn":[3.097372213],"iteration":960,"passed_time":0.5980590113,"remaining_time":0.02427086518},
{"learn":[3.095981813],"iteration":961,"passed_time":0.5985029891,"remaining_time":0.02364149021},
{"learn":[3.095347452],"iteration":962,"passed_time":0.5989453003,"remaining_time":0.02301243625},
{"learn":[3.094728409],"iteration":963,"passed_time":0.5994673667,"remaining_time":0.02238674813},
{"learn":[3.094118537],"iteration":964,"passed_time":0.5999730425,"remaining_time":0.0217606803},
{"learn":[3.093793695],"iteration":965,"passed_time":0.6005111568,"remaining_time":0.02113600345},
{"learn":[3.092581602],"iteration":966,"passed_time":0.6010413748,"remaining_time":0.02051123616},
{"learn":[3.091694202],"iteration":967,"passed_time":0.6016195285,"remaining_time":0.01988824888},
{"learn":[3.090298312],"iteration":968,"passed_time":0.6020793773,"remaining_time":0.01926156934},
{"learn":[3.090020107],"iteration":969,"passed_time":0.6025192323,"remaining_time":0.01863461543},
{"learn":[3.088949869],"iteration":970,"passed_time":0.6029568327,"remaining_time":0.01800797956},
{"learn":[3.086700204],"iteration":971,"passed_time":0.6033877885,"remaining_time":0.01738154123},
{"learn":[3.086584317],"iteration":972,"passed_time":0.6038251989,"remaining_time":0.01675568383},
{"learn":[3.084850742],"iteration":973,"passed_time":0.6042537055,"remaining_time":0.01612997571},
{"learn":[3.084239948],"iteration":974,"passed_time":0.6047160877,"remaining_time":0.01550554071},
{"learn":[3.082561673],"iteration":975,"passed_time":0.6051704965,"remaining_time":0.01488124172},
{"learn":[3.07991814],"iteration":976,"passed_time":0.6056054937,"remaining_time":0.01425683353},
{"learn":[3.079350277],"iteration":977,"passed_time":0.6061101616,"remaining_time":0.01363437991},
{"learn":[3.077637462],"iteration":978,"passed_time":0.6066482392,"remaining_time":0.01301288358},
{"learn":[3.076733301],"iteration":979,"passed_time":0.6071538924,"remaining_time":0.01239089576},
{"learn":[3.07594065],"iteration":980,"passed_time":0.6076549799,"remaining_time":0.0117690567},
{"learn":[3.072594655],"iteration":981,"passed_time":0.6081452541,"remaining_time":0.01114726535},
{"learn":[3.071977674],"iteration":982,"passed_time":0.6085754961,"remaining_time":0.01052470339},
{"learn":[3.069532634],"iteration":983,"passed_time":0.6091484454,"remaining_time":0.009904852771},
{"learn":[3.068870784],"iteration":984,"passed_time":0.6096585839,"remaining_time":0.009284140871},
{"learn":[3.068801463],"iteration":985,"passed_time":0.6100901642,"remaining_time":0.008662537828},
{"learn":[3.067433249],"iteration":986,"passed_time":0.6105725378,"remaining_time":0.008041988846},
{"learn":[3.065611456],"iteration":987,"passed_time":0.6109970764,"remaining_time":0.007421017122},
{"learn":[3.063039162],"iteration":988,"passed_time":0.611449451,"remaining_time":0.006800752236},
{"learn":[3.06177873],"iteration":989,"passed_time":0.6119418245,"remaining_time":0.006181230551},
{"learn":[3.061689148],"iteration":990,"passed_time":0.6123650458,"remaining_time":0.005561337449},
{"learn":[3.058984039],"iteration":991,"passed_time":0.6127959579,"remaining_time":0.004941902886},
{"learn":[3.057492984],"iteration":992,"passed_time":0.6133220528,"remaining_time":0.004323519002},
{"learn":[3.057290731],"iteration":993,"passed_time":0.6137611428,"remaining_time":0.00370479563},
{"learn":[3.056068348],"iteration":994,"passed_time":0.6141886338,"remaining_time":0.003086375044},
{"learn":[3.054987307],"iteration":995,"passed_time":0.6146652902,"remaining_time":0.002468535302},
{"learn":[3.054200234],"iteration":996,"passed_time":0.6150880657,"remaining_time":0.001850816647},
{"learn":[3.052732869],"iteration":997,"passed_time":0.6155612041,"remaining_time":0.001233589587},
{"learn":[3.051787862],"iteration":998,"passed_time":0.6160821229,"remaining_time":0.0006166988217},
{"learn":[3.051366222],"iteration":999,"passed_time":0.6165538793,"remaining_time":0}
]}